cdr_4x_oversampling.v
// ============================================================================
// Clock Data Recovery (CDR) - 4x Oversampling
// ============================================================================
// Clock: 200MHz clk_link
// Manchester rate: ~50 Mbps (49.9968 Mbps exact)
// Oversample ratio: 4x (ideal for integer sampling)
//
// Architecture:
//   - 4-stage shift register for edge detection
//   - 4 selectable sampling phases (0-3)
//   - Phase quality tracking for drift compensation
//   - 3-state lock detection (UNLOCKED/LOCKING/LOCKED)
//
// Locking: 32 consecutive valid transitions required
// Unlock:  200 cycles without transition or sync loss
// Tracking range: ±150 ppm (covers 64 ppm initial offset)
// ============================================================================

module cdr_4x_oversampling (
    input  wire clk_link,     // 200MHz
    input  wire rst_n,
    input  wire manch_in,     // Manchester encoded input
    output wire bit_out,      // Recovered bit
    output wire bit_valid,    // Bit valid pulse (1 cycle per bit)
    output wire locked        // CDR lock status
);

    // ========================================================================
    // 4-stage shift register for edge detection
    // ========================================================================
    reg [3:0] sample_shift;

    always @(posedge clk_link) begin
        sample_shift <= {sample_shift[2:0], manch_in};
    end

    // Edge detection: check between samples 1 and 0 (200MHz domain)
    wire transition = (sample_shift[1] != sample_shift[0]);

    // ========================================================================
    // Phase quality tracking
    // ========================================================================
    // Measures if current phase samples in data eye center
    // Positive: sampling in stable region (00 or 11)
    // Negative: sampling near transition (01 or 10)
    reg signed [5:0] phase_quality;

    always @(posedge clk_link) begin
        if (!rst_n) begin
            phase_quality <= 6'sd0;
        end else if (bit_valid) begin
            // At bit center: check if samples 2:1 are stable
            if ((sample_shift[2:1] == 2'b00) || (sample_shift[2:1] == 2'b11))
                phase_quality <= phase_quality + 6'sd1;    // Good: in eye center
            else
                phase_quality <= phase_quality - 6'sd3;    // Bad: near edge, stronger penalty
        end
    end

    // ========================================================================
    // Phase selection (4 positions: 0-3)
    // ========================================================================
    // 0: Early (before transition)
    // 1: Slightly early (good for locked state)
    // 2: Center (optimal sampling point)
    // 3: Late (after transition)
    reg [1:0] phase_sel;

    always @(posedge clk_link) begin
        if (!rst_n) begin
            phase_sel <= 2'b01;  // Default: slightly early position
        end else if (phase_quality <= -16) begin
            // Quality too low: move to later phase
            phase_sel <= phase_sel + 1'b1;
        end else if (phase_quality >= 8) begin
            // Good quality but can optimize: move earlier
            phase_sel <= phase_sel - 1'b1;
        end
    end

    // ========================================================================
    // Bit period counter (4 cycles per bit)
    // ========================================================================
    reg [1:0] sample_cnt;


    // Logic moved to main state machine for synchronization

    // Bit output and valid signal (sample at bit center: sample_cnt == 1)
    wire at_bit_center = (sample_cnt == 2'b01);
    assign bit_out   = sample_shift[phase_sel];
    assign bit_valid = locked && at_bit_center;

    // ========================================================================
    // Lock detection state machine
    // ========================================================================
    localparam STATE_UNLOCKED = 2'b00;
    localparam STATE_LOCKING  = 2'b01;
    localparam STATE_LOCKED   = 2'b10;

    reg [1:0] lock_state;
    reg [7:0] lock_timer;  // Counts transitions in LOCKING, inactivity in LOCKED

    always @(posedge clk_link) begin
        if (!rst_n) begin
            lock_state <= STATE_UNLOCKED;
            lock_timer <= 8'h00;
            sample_cnt <= 2'b00;
        end else begin
            sample_cnt <= sample_cnt + 1'b1; // Default increment

            case (lock_state)
                // UNLOCKED: Search for valid Manchester transitions
                STATE_UNLOCKED: begin
                    if (transition) begin
                        lock_state <= STATE_LOCKING;
                        lock_timer <= 8'h01;
                        // Align sample counter to transition
                        // We want sample_cnt=1 (at_bit_center) at the NEXT transition (8 cycles later)
                        // So set current sample_cnt to 2
                        sample_cnt <= 2'b10;
                    end
                end

                // LOCKING: Count consecutive valid bits
                STATE_LOCKING: begin
                    if (at_bit_center && transition) begin
                        // Valid Manchester transition at expected position
                        lock_timer <= lock_timer + 1'b1;
                        if (lock_timer >= 32) begin
                            // 32 consecutive valid bits achieved
                            lock_state <= STATE_LOCKED;
                            lock_timer <= 8'h00;
                        end
                    end else if (at_bit_center && !transition) begin
                        // Missing transition - Manchester violation
                        lock_state <= STATE_UNLOCKED;
                        lock_timer <= 8'h00;
                    end
                end

                // LOCKED: Monitor for loss of signal
                STATE_LOCKED: begin
                    // Count cycles without transition
                    if (!transition && (lock_timer < 200))
                        lock_timer <= lock_timer + 1'b1;
                    else if (transition)
                        lock_timer <= 8'h00;

                    // Unlock if too long without transition (signal lost)
                    if (lock_timer >= 200)
                        lock_state <= STATE_UNLOCKED;
                end

                default: begin
                    lock_state <= STATE_UNLOCKED;
                    lock_timer <= 8'h00;
                end
            endcase
        end
    end

    assign locked = (lock_state == STATE_LOCKED);

endmodule

testbench/tb_cdr.v
`timescale 1ns / 1ps

module tb_cdr;

    reg clk_link;
    reg rst_n;
    reg manch_in;
    wire bit_out;
    wire bit_valid;
    wire locked;

    // Clock generation (200MHz)
    initial begin
        clk_link = 0;
        forever #2.5 clk_link = ~clk_link;
    end

    // DUT
    cdr_4x_oversampling u_dut (
        .clk_link(clk_link),
        .rst_n(rst_n),
        .manch_in(manch_in),
        .bit_out(bit_out),
        .bit_valid(bit_valid),
        .locked(locked)
    );

    // Generate Manchester stream
    task send_bit(input reg b);
        begin
            // 50Mbps = 20ns period
            // 0 -> 01, 1 -> 10
            if (b == 0) begin
                manch_in = 0;
                #10;
                manch_in = 1;
                #10;
            end else begin
                manch_in = 1;
                #10;
                manch_in = 0;
                #10;
            end
        end
    endtask

    initial begin
        $dumpfile("tb_cdr.vcd");
        $dumpvars(0, tb_cdr);

        rst_n = 0;
        manch_in = 0;

        #100;
        rst_n = 1;
        
        // Send training sequence (alternating 1s and 0s)
        repeat(100) begin
            send_bit(1);
            send_bit(0);
        end

        wait(locked);
        $display("CDR Locked");

        // Send data
        send_bit(1);
        send_bit(1);
        send_bit(0);
        send_bit(1);

        #1000;
        $finish;
    end

endmodule

testbench/tb_cdr.vcd
$date
	Thu Nov 20 16:27:52 2025
$end
$version
	Icarus Verilog
$end
$timescale
	1ps
$end
$scope module tb_cdr $end
$var wire 1 ! locked $end
$var wire 1 " bit_valid $end
$var wire 1 # bit_out $end
$var reg 1 $ clk_link $end
$var reg 1 % manch_in $end
$var reg 1 & rst_n $end
$scope module u_dut $end
$var wire 1 " bit_valid $end
$var wire 1 $ clk_link $end
$var wire 1 % manch_in $end
$var wire 1 & rst_n $end
$var wire 1 ' transition $end
$var wire 1 ! locked $end
$var wire 1 # bit_out $end
$var wire 1 ( at_bit_center $end
$var parameter 2 ) STATE_LOCKED $end
$var parameter 2 * STATE_LOCKING $end
$var parameter 2 + STATE_UNLOCKED $end
$var reg 2 , lock_state [1:0] $end
$var reg 8 - lock_timer [7:0] $end
$var reg 6 . phase_quality [5:0] $end
$var reg 2 / phase_sel [1:0] $end
$var reg 2 0 sample_cnt [1:0] $end
$var reg 4 1 sample_shift [3:0] $end
$upscope $end
$scope task send_bit $end
$var reg 1 2 b $end
$upscope $end
$upscope $end
$enddefinitions $end
$comment Show the parameter values. $end
$dumpall
b0 +
b1 *
b10 )
$end
#0
$dumpvars
x2
bx 1
bx 0
bx /
bx .
bx -
bx ,
x(
x'
0&
0%
0$
x#
x"
x!
$end
#2500
0"
bx0 1
b0 .
b1 /
0(
b0 0
b0 -
0!
b0 ,
1$
#5000
0$
#7500
0'
0#
bx00 1
1$
#10000
0$
#12500
bx000 1
1$
#15000
0$
#17500
b0 1
1$
#20000
0$
#22500
1$
#25000
0$
#27500
1$
#30000
0$
#32500
1$
#35000
0$
#37500
1$
#40000
0$
#42500
1$
#45000
0$
#47500
1$
#50000
0$
#52500
1$
#55000
0$
#57500
1$
#60000
0$
#62500
1$
#65000
0$
#67500
1$
#70000
0$
#72500
1$
#75000
0$
#77500
1$
#80000
0$
#82500
1$
#85000
0$
#87500
1$
#90000
0$
#92500
1$
#95000
0$
#97500
1$
#100000
0$
1%
12
1&
#102500
1'
b1 1
1(
b1 0
1$
#105000
0$
#107500
0'
b1 -
b1 ,
0(
b10 0
1#
b11 1
1$
#110000
0$
0%
#112500
1'
b110 1
b11 0
1$
#115000
0$
#117500
0'
b0 0
0#
b1100 1
1$
#120000
0$
02
#122500
b1000 1
1(
b1 0
1$
#125000
0$
#127500
b0 -
b0 ,
0(
b10 0
b0 1
1$
#130000
0$
1%
#132500
1'
b1 1
b11 0
1$
#135000
0$
#137500
0'
b1 -
b1 ,
b10 0
1#
b11 1
1$
#140000
0$
12
#142500
b111 1
b11 0
1$
#145000
0$
#147500
b0 0
b1111 1
1$
#150000
0$
0%
#152500
1'
b1110 1
1(
b1 0
1$
#155000
0$
#157500
0'
b10 -
0(
b10 0
0#
b1100 1
1$
#160000
0$
02
#162500
b1000 1
b11 0
1$
#165000
0$
#167500
b0 0
b0 1
1$
#170000
0$
1%
#172500
1'
b1 1
1(
b1 0
1$
#175000
0$
#177500
0'
b11 -
0(
b10 0
1#
b11 1
1$
#180000
0$
12
#182500
b111 1
b11 0
1$
#185000
0$
#187500
b0 0
b1111 1
1$
#190000
0$
0%
#192500
1'
b1110 1
1(
b1 0
1$
#195000
0$
#197500
0'
b100 -
0(
b10 0
0#
b1100 1
1$
#200000
0$
02
#202500
b1000 1
b11 0
1$
#205000
0$
#207500
b0 0
b0 1
1$
#210000
0$
1%
#212500
1'
b1 1
1(
b1 0
1$
#215000
0$
#217500
0'
b101 -
0(
b10 0
1#
b11 1
1$
#220000
0$
12
#222500
b111 1
b11 0
1$
#225000
0$
#227500
b0 0
b1111 1
1$
#230000
0$
0%
#232500
1'
b1110 1
1(
b1 0
1$
#235000
0$
#237500
0'
b110 -
0(
b10 0
0#
b1100 1
1$
#240000
0$
02
#242500
b1000 1
b11 0
1$
#245000
0$
#247500
b0 0
b0 1
1$
#250000
0$
1%
#252500
1'
b1 1
1(
b1 0
1$
#255000
0$
#257500
0'
b111 -
0(
b10 0
1#
b11 1
1$
#260000
0$
12
#262500
b111 1
b11 0
1$
#265000
0$
#267500
b0 0
b1111 1
1$
#270000
0$
0%
#272500
1'
b1110 1
1(
b1 0
1$
#275000
0$
#277500
0'
b1000 -
0(
b10 0
0#
b1100 1
1$
#280000
0$
02
#282500
b1000 1
b11 0
1$
#285000
0$
#287500
b0 0
b0 1
1$
#290000
0$
1%
#292500
1'
b1 1
1(
b1 0
1$
#295000
0$
#297500
0'
b1001 -
0(
b10 0
1#
b11 1
1$
#300000
0$
12
#302500
b111 1
b11 0
1$
#305000
0$
#307500
b0 0
b1111 1
1$
#310000
0$
0%
#312500
1'
b1110 1
1(
b1 0
1$
#315000
0$
#317500
0'
b1010 -
0(
b10 0
0#
b1100 1
1$
#320000
0$
02
#322500
b1000 1
b11 0
1$
#325000
0$
#327500
b0 0
b0 1
1$
#330000
0$
1%
#332500
1'
b1 1
1(
b1 0
1$
#335000
0$
#337500
0'
b1011 -
0(
b10 0
1#
b11 1
1$
#340000
0$
12
#342500
b111 1
b11 0
1$
#345000
0$
#347500
b0 0
b1111 1
1$
#350000
0$
0%
#352500
1'
b1110 1
1(
b1 0
1$
#355000
0$
#357500
0'
b1100 -
0(
b10 0
0#
b1100 1
1$
#360000
0$
02
#362500
b1000 1
b11 0
1$
#365000
0$
#367500
b0 0
b0 1
1$
#370000
0$
1%
#372500
1'
b1 1
1(
b1 0
1$
#375000
0$
#377500
0'
b1101 -
0(
b10 0
1#
b11 1
1$
#380000
0$
12
#382500
b111 1
b11 0
1$
#385000
0$
#387500
b0 0
b1111 1
1$
#390000
0$
0%
#392500
1'
b1110 1
1(
b1 0
1$
#395000
0$
#397500
0'
b1110 -
0(
b10 0
0#
b1100 1
1$
#400000
0$
02
#402500
b1000 1
b11 0
1$
#405000
0$
#407500
b0 0
b0 1
1$
#410000
0$
1%
#412500
1'
b1 1
1(
b1 0
1$
#415000
0$
#417500
0'
b1111 -
0(
b10 0
1#
b11 1
1$
#420000
0$
12
#422500
b111 1
b11 0
1$
#425000
0$
#427500
b0 0
b1111 1
1$
#430000
0$
0%
#432500
1'
b1110 1
1(
b1 0
1$
#435000
0$
#437500
0'
b10000 -
0(
b10 0
0#
b1100 1
1$
#440000
0$
02
#442500
b1000 1
b11 0
1$
#445000
0$
#447500
b0 0
b0 1
1$
#450000
0$
1%
#452500
1'
b1 1
1(
b1 0
1$
#455000
0$
#457500
0'
b10001 -
0(
b10 0
1#
b11 1
1$
#460000
0$
12
#462500
b111 1
b11 0
1$
#465000
0$
#467500
b0 0
b1111 1
1$
#470000
0$
0%
#472500
1'
b1110 1
1(
b1 0
1$
#475000
0$
#477500
0'
b10010 -
0(
b10 0
0#
b1100 1
1$
#480000
0$
02
#482500
b1000 1
b11 0
1$
#485000
0$
#487500
b0 0
b0 1
1$
#490000
0$
1%
#492500
1'
b1 1
1(
b1 0
1$
#495000
0$
#497500
0'
b10011 -
0(
b10 0
1#
b11 1
1$
#500000
0$
12
#502500
b111 1
b11 0
1$
#505000
0$
#507500
b0 0
b1111 1
1$
#510000
0$
0%
#512500
1'
b1110 1
1(
b1 0
1$
#515000
0$
#517500
0'
b10100 -
0(
b10 0
0#
b1100 1
1$
#520000
0$
02
#522500
b1000 1
b11 0
1$
#525000
0$
#527500
b0 0
b0 1
1$
#530000
0$
1%
#532500
1'
b1 1
1(
b1 0
1$
#535000
0$
#537500
0'
b10101 -
0(
b10 0
1#
b11 1
1$
#540000
0$
12
#542500
b111 1
b11 0
1$
#545000
0$
#547500
b0 0
b1111 1
1$
#550000
0$
0%
#552500
1'
b1110 1
1(
b1 0
1$
#555000
0$
#557500
0'
b10110 -
0(
b10 0
0#
b1100 1
1$
#560000
0$
02
#562500
b1000 1
b11 0
1$
#565000
0$
#567500
b0 0
b0 1
1$
#570000
0$
1%
#572500
1'
b1 1
1(
b1 0
1$
#575000
0$
#577500
0'
b10111 -
0(
b10 0
1#
b11 1
1$
#580000
0$
12
#582500
b111 1
b11 0
1$
#585000
0$
#587500
b0 0
b1111 1
1$
#590000
0$
0%
#592500
1'
b1110 1
1(
b1 0
1$
#595000
0$
#597500
0'
b11000 -
0(
b10 0
0#
b1100 1
1$
#600000
0$
02
#602500
b1000 1
b11 0
1$
#605000
0$
#607500
b0 0
b0 1
1$
#610000
0$
1%
#612500
1'
b1 1
1(
b1 0
1$
#615000
0$
#617500
0'
b11001 -
0(
b10 0
1#
b11 1
1$
#620000
0$
12
#622500
b111 1
b11 0
1$
#625000
0$
#627500
b0 0
b1111 1
1$
#630000
0$
0%
#632500
1'
b1110 1
1(
b1 0
1$
#635000
0$
#637500
0'
b11010 -
0(
b10 0
0#
b1100 1
1$
#640000
0$
02
#642500
b1000 1
b11 0
1$
#645000
0$
#647500
b0 0
b0 1
1$
#650000
0$
1%
#652500
1'
b1 1
1(
b1 0
1$
#655000
0$
#657500
0'
b11011 -
0(
b10 0
1#
b11 1
1$
#660000
0$
12
#662500
b111 1
b11 0
1$
#665000
0$
#667500
b0 0
b1111 1
1$
#670000
0$
0%
#672500
1'
b1110 1
1(
b1 0
1$
#675000
0$
#677500
0'
b11100 -
0(
b10 0
0#
b1100 1
1$
#680000
0$
02
#682500
b1000 1
b11 0
1$
#685000
0$
#687500
b0 0
b0 1
1$
#690000
0$
1%
#692500
1'
b1 1
1(
b1 0
1$
#695000
0$
#697500
0'
b11101 -
0(
b10 0
1#
b11 1
1$
#700000
0$
12
#702500
b111 1
b11 0
1$
#705000
0$
#707500
b0 0
b1111 1
1$
#710000
0$
0%
#712500
1'
b1110 1
1(
b1 0
1$
#715000
0$
#717500
0'
b11110 -
0(
b10 0
0#
b1100 1
1$
#720000
0$
02
#722500
b1000 1
b11 0
1$
#725000
0$
#727500
b0 0
b0 1
1$
#730000
0$
1%
#732500
1'
b1 1
1(
b1 0
1$
#735000
0$
#737500
0'
b11111 -
0(
b10 0
1#
b11 1
1$
#740000
0$
12
#742500
b111 1
b11 0
1$
#745000
0$
#747500
b0 0
b1111 1
1$
#750000
0$
0%
#752500
1'
b1110 1
1(
b1 0
1$
#755000
0$
#757500
0'
b100000 -
0(
b10 0
0#
b1100 1
1$
#760000
0$
02
#762500
b1000 1
b11 0
1$
#765000
0$
#767500
b0 0
b0 1
1$
#770000
0$
1%
#772500
1'
b1 1
1(
b1 0
1$
#775000
0$
#777500
0'
1!
b10 ,
b0 -
0(
b10 0
1#
b11 1
1$
#780000
0$
12
#782500
b111 1
b1 -
b11 0
1$
#785000
0$
#787500
b10 -
b0 0
b1111 1
1$
#790000
0$
0%
#792500
1'
1"
b1110 1
b11 -
1(
b1 0
1$
#795000
0$
#797500
0'
0"
b0 -
0(
b10 0
b1 .
0#
b1100 1
1$
#800000
0$
02
#802500
b1000 1
b1 -
b11 0
1$
#805000
0$
#807500
b10 -
b0 0
b0 1
1$
#810000
0$
1%
#812500
1'
1"
b1 1
b11 -
1(
b1 0
1$
#815000
0$
#817500
0'
0"
b0 -
0(
b10 0
b10 .
1#
b11 1
1$
#820000
0$
12
#822500
b111 1
b1 -
b11 0
1$
#825000
0$
#827500
b10 -
b0 0
b1111 1
1$
#830000
0$
0%
#832500
1'
1"
b1110 1
b11 -
1(
b1 0
1$
#835000
0$
#837500
0'
0"
b0 -
0(
b10 0
b11 .
0#
b1100 1
1$
#840000
0$
02
#842500
b1000 1
b1 -
b11 0
1$
#845000
0$
#847500
b10 -
b0 0
b0 1
1$
#850000
0$
1%
#852500
1'
1"
b1 1
b11 -
1(
b1 0
1$
#855000
0$
#857500
0'
0"
b0 -
0(
b10 0
b100 .
1#
b11 1
1$
#860000
0$
12
#862500
b111 1
b1 -
b11 0
1$
#865000
0$
#867500
b10 -
b0 0
b1111 1
1$
#870000
0$
0%
#872500
1'
1"
b1110 1
b11 -
1(
b1 0
1$
#875000
0$
#877500
0'
0"
b0 -
0(
b10 0
b101 .
0#
b1100 1
1$
#880000
0$
02
#882500
b1000 1
b1 -
b11 0
1$
#885000
0$
#887500
b10 -
b0 0
b0 1
1$
#890000
0$
1%
#892500
1'
1"
b1 1
b11 -
1(
b1 0
1$
#895000
0$
#897500
0'
0"
b0 -
0(
b10 0
b110 .
1#
b11 1
1$
#900000
0$
12
#902500
b111 1
b1 -
b11 0
1$
#905000
0$
#907500
b10 -
b0 0
b1111 1
1$
#910000
0$
0%
#912500
1'
1"
b1110 1
b11 -
1(
b1 0
1$
#915000
0$
#917500
0'
0"
b0 -
0(
b10 0
b111 .
0#
b1100 1
1$
#920000
0$
02
#922500
b1000 1
b1 -
b11 0
1$
#925000
0$
#927500
b10 -
b0 0
b0 1
1$
#930000
0$
1%
#932500
1'
1"
b1 1
b11 -
1(
b1 0
1$
#935000
0$
#937500
0'
0"
b0 -
0(
b10 0
b1000 .
1#
b11 1
1$
#940000
0$
12
#942500
b111 1
b0 /
b1 -
b11 0
1$
#945000
0$
#947500
b10 -
b0 0
b11 /
b1111 1
1$
#950000
0$
0%
#952500
1'
1"
b1110 1
b10 /
b11 -
1(
b1 0
1$
#955000
0$
#957500
0'
0"
b0 -
0(
b10 0
0#
b1 /
b1001 .
b1100 1
1$
#960000
0$
02
#962500
b1000 1
b0 /
b1 -
b11 0
1$
#965000
0$
#967500
b10 -
b0 0
b11 /
b0 1
1$
#970000
0$
1%
#972500
1'
1"
b1 1
b10 /
b11 -
1(
b1 0
1$
#975000
0$
#977500
0'
0"
b0 -
0(
b10 0
1#
b1 /
b1010 .
b11 1
1$
#980000
0$
12
#982500
b111 1
b0 /
b1 -
b11 0
1$
#985000
0$
#987500
b10 -
b0 0
b11 /
b1111 1
1$
#990000
0$
0%
#992500
1'
1"
b1110 1
b10 /
b11 -
1(
b1 0
1$
#995000
0$
#997500
0'
0"
b0 -
0(
b10 0
0#
b1 /
b1011 .
b1100 1
1$
#1000000
0$
02
#1002500
b1000 1
b0 /
b1 -
b11 0
1$
#1005000
0$
#1007500
b10 -
b0 0
b11 /
b0 1
1$
#1010000
0$
1%
#1012500
1'
1"
b1 1
b10 /
b11 -
1(
b1 0
1$
#1015000
0$
#1017500
0'
0"
b0 -
0(
b10 0
1#
b1 /
b1100 .
b11 1
1$
#1020000
0$
12
#1022500
b111 1
b0 /
b1 -
b11 0
1$
#1025000
0$
#1027500
b10 -
b0 0
b11 /
b1111 1
1$
#1030000
0$
0%
#1032500
1'
1"
b1110 1
b10 /
b11 -
1(
b1 0
1$
#1035000
0$
#1037500
0'
0"
b0 -
0(
b10 0
0#
b1 /
b1101 .
b1100 1
1$
#1040000
0$
02
#1042500
b1000 1
b0 /
b1 -
b11 0
1$
#1045000
0$
#1047500
b10 -
b0 0
b11 /
b0 1
1$
#1050000
0$
1%
#1052500
1'
1"
b1 1
b10 /
b11 -
1(
b1 0
1$
#1055000
0$
#1057500
0'
0"
b0 -
0(
b10 0
1#
b1 /
b1110 .
b11 1
1$
#1060000
0$
12
#1062500
b111 1
b0 /
b1 -
b11 0
1$
#1065000
0$
#1067500
b10 -
b0 0
b11 /
b1111 1
1$
#1070000
0$
0%
#1072500
1'
1"
b1110 1
b10 /
b11 -
1(
b1 0
1$
#1075000
0$
#1077500
0'
0"
b0 -
0(
b10 0
0#
b1 /
b1111 .
b1100 1
1$
#1080000
0$
02
#1082500
b1000 1
b0 /
b1 -
b11 0
1$
#1085000
0$
#1087500
b10 -
b0 0
b11 /
b0 1
1$
#1090000
0$
1%
#1092500
1'
1"
b1 1
b10 /
b11 -
1(
b1 0
1$
#1095000
0$
#1097500
0'
0"
b0 -
0(
b10 0
1#
b1 /
b10000 .
b11 1
1$
#1100000
0$
12
#1102500
b111 1
b0 /
b1 -
b11 0
1$
#1105000
0$
#1107500
b10 -
b0 0
b11 /
b1111 1
1$
#1110000
0$
0%
#1112500
1'
1"
b1110 1
b10 /
b11 -
1(
b1 0
1$
#1115000
0$
#1117500
0'
0"
b0 -
0(
b10 0
0#
b1 /
b10001 .
b1100 1
1$
#1120000
0$
02
#1122500
b1000 1
b0 /
b1 -
b11 0
1$
#1125000
0$
#1127500
b10 -
b0 0
b11 /
b0 1
1$
#1130000
0$
1%
#1132500
1'
1"
b1 1
b10 /
b11 -
1(
b1 0
1$
#1135000
0$
#1137500
0'
0"
b0 -
0(
b10 0
1#
b1 /
b10010 .
b11 1
1$
#1140000
0$
12
#1142500
b111 1
b0 /
b1 -
b11 0
1$
#1145000
0$
#1147500
b10 -
b0 0
b11 /
b1111 1
1$
#1150000
0$
0%
#1152500
1'
1"
b1110 1
b10 /
b11 -
1(
b1 0
1$
#1155000
0$
#1157500
0'
0"
b0 -
0(
b10 0
0#
b1 /
b10011 .
b1100 1
1$
#1160000
0$
02
#1162500
b1000 1
b0 /
b1 -
b11 0
1$
#1165000
0$
#1167500
b10 -
b0 0
b11 /
b0 1
1$
#1170000
0$
1%
#1172500
1'
1"
b1 1
b10 /
b11 -
1(
b1 0
1$
#1175000
0$
#1177500
0'
0"
b0 -
0(
b10 0
1#
b1 /
b10100 .
b11 1
1$
#1180000
0$
12
#1182500
b111 1
b0 /
b1 -
b11 0
1$
#1185000
0$
#1187500
b10 -
b0 0
b11 /
b1111 1
1$
#1190000
0$
0%
#1192500
1'
1"
b1110 1
b10 /
b11 -
1(
b1 0
1$
#1195000
0$
#1197500
0'
0"
b0 -
0(
b10 0
0#
b1 /
b10101 .
b1100 1
1$
#1200000
0$
02
#1202500
b1000 1
b0 /
b1 -
b11 0
1$
#1205000
0$
#1207500
b10 -
b0 0
b11 /
b0 1
1$
#1210000
0$
1%
#1212500
1'
1"
b1 1
b10 /
b11 -
1(
b1 0
1$
#1215000
0$
#1217500
0'
0"
b0 -
0(
b10 0
1#
b1 /
b10110 .
b11 1
1$
#1220000
0$
12
#1222500
b111 1
b0 /
b1 -
b11 0
1$
#1225000
0$
#1227500
b10 -
b0 0
b11 /
b1111 1
1$
#1230000
0$
0%
#1232500
1'
1"
b1110 1
b10 /
b11 -
1(
b1 0
1$
#1235000
0$
#1237500
0'
0"
b0 -
0(
b10 0
0#
b1 /
b10111 .
b1100 1
1$
#1240000
0$
02
#1242500
b1000 1
b0 /
b1 -
b11 0
1$
#1245000
0$
#1247500
b10 -
b0 0
b11 /
b0 1
1$
#1250000
0$
1%
#1252500
1'
1"
b1 1
b10 /
b11 -
1(
b1 0
1$
#1255000
0$
#1257500
0'
0"
b0 -
0(
b10 0
1#
b1 /
b11000 .
b11 1
1$
#1260000
0$
12
#1262500
b111 1
b0 /
b1 -
b11 0
1$
#1265000
0$
#1267500
b10 -
b0 0
b11 /
b1111 1
1$
#1270000
0$
0%
#1272500
1'
1"
b1110 1
b10 /
b11 -
1(
b1 0
1$
#1275000
0$
#1277500
0'
0"
b0 -
0(
b10 0
0#
b1 /
b11001 .
b1100 1
1$
#1280000
0$
02
#1282500
b1000 1
b0 /
b1 -
b11 0
1$
#1285000
0$
#1287500
b10 -
b0 0
b11 /
b0 1
1$
#1290000
0$
1%
#1292500
1'
1"
b1 1
b10 /
b11 -
1(
b1 0
1$
#1295000
0$
#1297500
0'
0"
b0 -
0(
b10 0
1#
b1 /
b11010 .
b11 1
1$
#1300000
0$
12
#1302500
b111 1
b0 /
b1 -
b11 0
1$
#1305000
0$
#1307500
b10 -
b0 0
b11 /
b1111 1
1$
#1310000
0$
0%
#1312500
1'
1"
b1110 1
b10 /
b11 -
1(
b1 0
1$
#1315000
0$
#1317500
0'
0"
b0 -
0(
b10 0
0#
b1 /
b11011 .
b1100 1
1$
#1320000
0$
02
#1322500
b1000 1
b0 /
b1 -
b11 0
1$
#1325000
0$
#1327500
b10 -
b0 0
b11 /
b0 1
1$
#1330000
0$
1%
#1332500
1'
1"
b1 1
b10 /
b11 -
1(
b1 0
1$
#1335000
0$
#1337500
0'
0"
b0 -
0(
b10 0
1#
b1 /
b11100 .
b11 1
1$
#1340000
0$
12
#1342500
b111 1
b0 /
b1 -
b11 0
1$
#1345000
0$
#1347500
b10 -
b0 0
b11 /
b1111 1
1$
#1350000
0$
0%
#1352500
1'
1"
b1110 1
b10 /
b11 -
1(
b1 0
1$
#1355000
0$
#1357500
0'
0"
b0 -
0(
b10 0
0#
b1 /
b11101 .
b1100 1
1$
#1360000
0$
02
#1362500
b1000 1
b0 /
b1 -
b11 0
1$
#1365000
0$
#1367500
b10 -
b0 0
b11 /
b0 1
1$
#1370000
0$
1%
#1372500
1'
1"
b1 1
b10 /
b11 -
1(
b1 0
1$
#1375000
0$
#1377500
0'
0"
b0 -
0(
b10 0
1#
b1 /
b11110 .
b11 1
1$
#1380000
0$
12
#1382500
b111 1
b0 /
b1 -
b11 0
1$
#1385000
0$
#1387500
b10 -
b0 0
b11 /
b1111 1
1$
#1390000
0$
0%
#1392500
1'
1"
b1110 1
b10 /
b11 -
1(
b1 0
1$
#1395000
0$
#1397500
0'
0"
b0 -
0(
b10 0
0#
b1 /
b11111 .
b1100 1
1$
#1400000
0$
02
#1402500
b1000 1
b0 /
b1 -
b11 0
1$
#1405000
0$
#1407500
b10 -
b0 0
b11 /
b0 1
1$
#1410000
0$
1%
#1412500
1'
1"
b1 1
b10 /
b11 -
1(
b1 0
1$
#1415000
0$
#1417500
0'
0"
b0 -
0(
b10 0
1#
b1 /
b100000 .
b11 1
1$
#1420000
0$
12
#1422500
b111 1
1#
b10 /
b1 -
b11 0
1$
#1425000
0$
#1427500
b10 -
b0 0
b11 /
b1111 1
1$
#1430000
0$
0%
#1432500
1'
1"
0#
b1110 1
b0 /
b11 -
1(
b1 0
1$
#1435000
0$
#1437500
0'
0"
b0 -
0(
b10 0
b1 /
b100001 .
b1100 1
1$
#1440000
0$
02
#1442500
b1000 1
0#
b10 /
b1 -
b11 0
1$
#1445000
0$
#1447500
b10 -
b0 0
b11 /
b0 1
1$
#1450000
0$
1%
#1452500
1'
1"
1#
b1 1
b0 /
b11 -
1(
b1 0
1$
#1455000
0$
#1457500
0'
0"
b0 -
0(
b10 0
b1 /
b100010 .
b11 1
1$
#1460000
0$
12
#1462500
b111 1
1#
b10 /
b1 -
b11 0
1$
#1465000
0$
#1467500
b10 -
b0 0
b11 /
b1111 1
1$
#1470000
0$
0%
#1472500
1'
1"
0#
b1110 1
b0 /
b11 -
1(
b1 0
1$
#1475000
0$
#1477500
0'
0"
b0 -
0(
b10 0
b1 /
b100011 .
b1100 1
1$
#1480000
0$
02
#1482500
b1000 1
0#
b10 /
b1 -
b11 0
1$
#1485000
0$
#1487500
b10 -
b0 0
b11 /
b0 1
1$
#1490000
0$
1%
#1492500
1'
1"
1#
b1 1
b0 /
b11 -
1(
b1 0
1$
#1495000
0$
#1497500
0'
0"
b0 -
0(
b10 0
b1 /
b100100 .
b11 1
1$
#1500000
0$
12
#1502500
b111 1
1#
b10 /
b1 -
b11 0
1$
#1505000
0$
#1507500
b10 -
b0 0
b11 /
b1111 1
1$
#1510000
0$
0%
#1512500
1'
1"
0#
b1110 1
b0 /
b11 -
1(
b1 0
1$
#1515000
0$
#1517500
0'
0"
b0 -
0(
b10 0
b1 /
b100101 .
b1100 1
1$
#1520000
0$
02
#1522500
b1000 1
0#
b10 /
b1 -
b11 0
1$
#1525000
0$
#1527500
b10 -
b0 0
b11 /
b0 1
1$
#1530000
0$
1%
#1532500
1'
1"
1#
b1 1
b0 /
b11 -
1(
b1 0
1$
#1535000
0$
#1537500
0'
0"
b0 -
0(
b10 0
b1 /
b100110 .
b11 1
1$
#1540000
0$
12
#1542500
b111 1
1#
b10 /
b1 -
b11 0
1$
#1545000
0$
#1547500
b10 -
b0 0
b11 /
b1111 1
1$
#1550000
0$
0%
#1552500
1'
1"
0#
b1110 1
b0 /
b11 -
1(
b1 0
1$
#1555000
0$
#1557500
0'
0"
b0 -
0(
b10 0
b1 /
b100111 .
b1100 1
1$
#1560000
0$
02
#1562500
b1000 1
0#
b10 /
b1 -
b11 0
1$
#1565000
0$
#1567500
b10 -
b0 0
b11 /
b0 1
1$
#1570000
0$
1%
#1572500
1'
1"
1#
b1 1
b0 /
b11 -
1(
b1 0
1$
#1575000
0$
