frame_sync_100m.v
// ============================================================================
// Frame Synchronizer - 56-bit Frame Format
// ============================================================================
// Frame format: {SYNC(8), CNT(8), DATA(32), CRC(8)} = 56 bits
// SYNC pattern: 8'hAA
// CRC-8: Polynomial 0x07, initial 0x00
//
// State machine:
//   SEARCH: Look for SYNC pattern in 48-bit sliding window
//   SYNC:   Frame synced, validate CRC and output data
//   VERIFY: CRC validation state (1 cycle)
//
// Features:
//   - Sliding window sync (allows up to 7-bit slip)
//   - Frame counter continuity check
//   - CRC error detection
//   - Auto-resync after 8 consecutive CRC errors
// ============================================================================

module frame_sync_100m (
    input  wire clk_sys,      // 100MHz
    input  wire rst_n,
    input  wire bit_in,       // From CDR
    input  wire bit_valid,
    output reg  [31:0] data_out,
    output reg        data_valid,
    output reg        frame_error,
    output reg        sync_lost
);

    localparam SYNC_PATTERN = 8'hAA;

    // ========================================================================
    // State machine
    // ========================================================================
    localparam SEARCH = 2'b00;
    localparam SYNC   = 2'b01;
    localparam VERIFY = 2'b10;

    reg [1:0] state;
    reg [5:0] bit_cnt;      // 0-55 (56 bits per frame)
    reg [7:0] frame_cnt;    // Expected frame counter
    reg [3:0] error_cnt;    // Consecutive CRC errors

    // ========================================================================
    // 56-bit shift register
    // ========================================================================
    reg [55:0] shift_reg;

    always @(posedge clk_sys) begin
        if (bit_valid) begin
            shift_reg <= {shift_reg[54:0], bit_in};
            $display("Frame Sync: Shift Reg: %h", {shift_reg[54:0], bit_in});
        end
    end

    // ========================================================================
    // CRC-8 calculation (combination logic, x^8 + x^2 + x + 1)
    // ========================================================================
    wire [7:0] calc_crc;
    assign calc_crc = crc8_48bit({shift_reg[55:8]});

    function [7:0] crc8_48bit;
        input [47:0] data;
        integer i;
        reg [7:0] crc;
        begin
            crc = 8'h00;
            for (i = 47; i >= 0; i = i - 1) begin
                if ((crc[7] ^ data[i]) == 1'b1)
                    crc = {crc[6:0], 1'b0} ^ 8'h07;  // Polynomial: x^8 + x^2 + x + 1
                else
                    crc = {crc[6:0], 1'b0};
            end
            crc8_48bit = crc;
        end
    endfunction

    // ========================================================================
    // Main state machine
    // ========================================================================
    always @(posedge clk_sys or negedge rst_n) begin
        if (!rst_n) begin
            state      <= SEARCH;
            bit_cnt    <= 6'b0;
            frame_cnt  <= 8'b0;
            error_cnt  <= 4'b0;
            data_valid <= 1'b0;
            frame_error <= 1'b0;
            sync_lost  <= 1'b0;
        end else begin
            data_valid  <= 1'b0;  // Default
            frame_error <= 1'b0;
            sync_lost   <= 1'b0;

            case (state)
                // SEARCH: Look for SYNC pattern
                // SEARCH: Look for SYNC pattern
                SEARCH: begin
                    if (shift_reg[55:48] == SYNC_PATTERN) begin
                        // Found potential frame start - Check CRC immediately
                        $display("Frame Sync: Potential Sync at %t, CRC calc: %h, CRC in: %h", $time, calc_crc, shift_reg[7:0]);
                        if (calc_crc == shift_reg[7:0]) begin
                            // Good frame
                            error_cnt <= 4'b0;

                            // Check frame counter continuity (if we were tracking)
                            if (shift_reg[47:40] != frame_cnt) begin
                                // If we were searching, we might have skipped frames, 
                                // so this is expected, but we report it if we thought we were close?
                                // Actually, if we are in SEARCH, we might be starting up.
                                // Let's just report sync_lost if it mismatches, 
                                // but since we are in SEARCH, maybe we just accept it?
                                // The original VERIFY logic sets sync_lost. We'll do the same.
                                sync_lost <= 1'b1;
                            end

                            frame_cnt <= shift_reg[47:40] + 8'b1;

                            // Output data
                            data_out   <= shift_reg[39:8];
                            data_valid <= 1'b1;

                            // Transition to SYNC to wait for NEXT frame
                            state   <= SYNC;
                            bit_cnt <= 6'b0;
                        end
                    end
                end

                // SYNC: Accumulate frame bits
                SYNC: begin
                    if (bit_valid) begin
                        if (bit_cnt == 6'b110111) begin  // 55 (all 56 bits)
                            // Complete frame received
                            bit_cnt <= 6'b0;
                            state   <= VERIFY;
                        end else begin
                            bit_cnt <= bit_cnt + 1'b1;
                        end
                    end
                end

                // VERIFY: Check CRC and output data
                VERIFY: begin
                    // Check CRC
                    if (calc_crc == shift_reg[7:0]) begin
                        // Good frame
                        error_cnt <= 4'b0;

                        // Check frame counter continuity
                        if (shift_reg[47:40] != frame_cnt) begin
                            sync_lost <= 1'b1;
                        end

                        frame_cnt <= shift_reg[47:40] + 8'b1;

                        // Output data
                        data_out   <= shift_reg[39:8];
                        data_valid <= 1'b1;
                    end else begin
                        // CRC error
                        frame_error <= 1'b1;
                        error_cnt   <= error_cnt + 1'b1;

                        // Lost sync after 8 consecutive errors
                        if (error_cnt >= 4'b0111) begin
                            sync_lost <= 1'b1;
                            state     <= SEARCH;
                            frame_cnt <= 8'b0;
                        end
                    end

                    state <= SEARCH;  // Always return to search
                end

                default: begin
                    state <= SEARCH;
                end
            endcase
        end
    end

endmodule

testbench/tb_frame_sync.v
`timescale 1ns / 1ps

module tb_frame_sync;

    reg clk_sys;
    reg rst_n;
    reg bit_in;
    reg bit_valid;
    wire [31:0] data_out;
    wire data_valid;
    wire frame_error;
    wire sync_lost;

    // Clock generation (100MHz)
    initial begin
        clk_sys = 0;
        forever #5 clk_sys = ~clk_sys;
    end

    // DUT
    frame_sync_100m u_dut (
        .clk_sys(clk_sys),
        .rst_n(rst_n),
        .bit_in(bit_in),
        .bit_valid(bit_valid),
        .data_out(data_out),
        .data_valid(data_valid),
        .frame_error(frame_error),
        .sync_lost(sync_lost)
    );

    // Helper to calculate CRC
    function [7:0] calc_crc8;
        input [47:0] data;
        integer i;
        reg [7:0] crc;
        begin
            crc = 8'h00;
            for (i = 47; i >= 0; i = i - 1) begin
                if ((crc[7] ^ data[i]) == 1'b1)
                    crc = {crc[6:0], 1'b0} ^ 8'h07;
                else
                    crc = {crc[6:0], 1'b0};
            end
            calc_crc8 = crc;
        end
    endfunction

    task send_frame(input [7:0] cnt, input [31:0] data);
        reg [55:0] frame;
        reg [7:0] crc;
        integer i;
        begin
            // Construct frame: SYNC + CNT + DATA
            // CRC is calculated over SYNC + CNT + DATA
            frame[55:48] = 8'hAA; // SYNC
            frame[47:40] = cnt;
            frame[39:8]  = data;
            
            crc = calc_crc8(frame[55:8]);
            frame[7:0] = crc;

            $display("Sending Frame: %h", frame);

            for (i = 55; i >= 0; i = i - 1) begin
                @(posedge clk_sys);
                bit_in = frame[i];
                bit_valid = 1;
                @(posedge clk_sys); // Wait a cycle? No, bit_valid is pulse or level?
                // In frame_sync, it samples on posedge if bit_valid is high.
                // So we should hold bit_valid high for one cycle.
                // But here we are driving it.
                // Let's assume 1 bit per 4 clocks (since it comes from CDR/Manchester)
                // But frame_sync takes bit_in/bit_valid.
                // If we drive bit_valid high for 1 cycle, it consumes 1 bit.
                bit_valid = 0;
                repeat(3) @(posedge clk_sys); // Simulate 25Mbps rate (1 bit per 4 sys clocks)
            end
        end
    endtask

    initial begin
        $dumpfile("tb_frame_sync.vcd");
        $dumpvars(0, tb_frame_sync);

        rst_n = 0;
        bit_in = 0;
        bit_valid = 0;

        #100;
        rst_n = 1;
        
        // Send a few frames
        send_frame(8'h00, 32'h12345678);
        send_frame(8'h01, 32'h87654321);

        repeat(100) @(posedge clk_sys);
        $finish;
    end

endmodule

testbench/tb_frame_sync.vcd
$date
	Thu Nov 20 16:28:35 2025
$end
$version
	Icarus Verilog
$end
$timescale
	1ps
$end
$scope module tb_frame_sync $end
$var wire 1 ! sync_lost $end
$var wire 1 " frame_error $end
$var wire 1 # data_valid $end
$var wire 32 $ data_out [31:0] $end
$var reg 1 % bit_in $end
$var reg 1 & bit_valid $end
$var reg 1 ' clk_sys $end
$var reg 1 ( rst_n $end
$scope function calc_crc8 $end
$var reg 8 ) crc [7:0] $end
$var reg 48 * data [47:0] $end
$var integer 32 + i [31:0] $end
$upscope $end
$scope module u_dut $end
$var wire 1 % bit_in $end
$var wire 1 & bit_valid $end
$var wire 1 ' clk_sys $end
$var wire 1 ( rst_n $end
$var wire 8 , calc_crc [7:0] $end
$var parameter 2 - SEARCH $end
$var parameter 2 . SYNC $end
$var parameter 8 / SYNC_PATTERN $end
$var parameter 2 0 VERIFY $end
$var reg 6 1 bit_cnt [5:0] $end
$var reg 32 2 data_out [31:0] $end
$var reg 1 # data_valid $end
$var reg 4 3 error_cnt [3:0] $end
$var reg 8 4 frame_cnt [7:0] $end
$var reg 1 " frame_error $end
$var reg 56 5 shift_reg [55:0] $end
$var reg 2 6 state [1:0] $end
$var reg 1 ! sync_lost $end
$scope function crc8_48bit $end
$var reg 8 7 crc [7:0] $end
$var reg 48 8 data [47:0] $end
$var integer 32 9 i [31:0] $end
$upscope $end
$upscope $end
$scope task send_frame $end
$var reg 8 : cnt [7:0] $end
$var reg 8 ; crc [7:0] $end
$var reg 32 < data [31:0] $end
$var reg 56 = frame [55:0] $end
$var integer 32 > i [31:0] $end
$upscope $end
$upscope $end
$enddefinitions $end
$comment Show the parameter values. $end
$dumpall
b10 0
b10101010 /
b1 .
b0 -
$end
#0
$dumpvars
bx >
bx =
bx <
bx ;
bx :
b11111111111111111111111111111111 9
bx 8
b0 7
b0 6
bx 5
b0 4
b0 3
bx 2
b0 1
b0 ,
bx +
bx *
bx )
0(
0'
0&
0%
bx $
0#
0"
0!
$end
#5000
1'
#10000
0'
#15000
1'
#20000
0'
#25000
1'
#30000
0'
#35000
1'
#40000
0'
#45000
1'
#50000
0'
#55000
1'
#60000
0'
#65000
1'
#70000
0'
#75000
1'
#80000
0'
#85000
1'
#90000
0'
#95000
1'
#100000
0'
b110111 >
b11010110 ;
b11111111111111111111111111111111 +
b11010110 )
b101010100000000000010010001101000101011001111000 *
b10101010000000000001001000110100010101100111100011010110 =
b10010001101000101011001111000 <
b0 :
1(
#105000
bx1 5
1&
1%
1'
#110000
0'
#115000
bx11 5
0&
1'
#120000
0'
#125000
1'
#130000
0'
#135000
1'
#140000
0'
#145000
b110110 >
1'
#150000
0'
#155000
1&
0%
1'
#160000
0'
#165000
0&
1'
#170000
0'
#175000
1'
#180000
0'
#185000
1'
#190000
0'
#195000
b110101 >
1'
#200000
0'
#205000
bx111 5
1&
1%
1'
#210000
0'
#215000
bx1111 5
0&
1'
#220000
0'
#225000
1'
#230000
0'
#235000
1'
#240000
0'
#245000
b110100 >
1'
#250000
0'
#255000
1&
0%
1'
#260000
0'
#265000
0&
1'
#270000
0'
#275000
1'
#280000
0'
#285000
1'
#290000
0'
#295000
b110011 >
1'
#300000
0'
#305000
bx11111 5
1&
1%
1'
#310000
0'
#315000
bx111111 5
0&
1'
#320000
0'
#325000
1'
#330000
0'
#335000
1'
#340000
0'
#345000
b110010 >
1'
#350000
0'
#355000
1&
0%
1'
#360000
0'
#365000
0&
1'
#370000
0'
#375000
1'
#380000
0'
#385000
1'
#390000
0'
#395000
b110001 >
1'
#400000
0'
#405000
bx1111111 5
1&
1%
1'
#410000
0'
#415000
bx11111111 5
0&
1'
#420000
0'
#425000
1'
#430000
0'
#435000
1'
#440000
0'
#445000
b110000 >
1'
#450000
0'
#455000
1&
0%
1'
#460000
0'
#465000
0&
1'
#470000
0'
#475000
1'
#480000
0'
#485000
1'
#490000
0'
#495000
b101111 >
1'
#500000
0'
#505000
b111 ,
b111 7
b11111111111111111111111111111111 9
bx1 8
bx111111110 5
1&
1'
#510000
0'
#515000
b1001 ,
b11111111111111111111111111111111 9
b1001 7
bx11 8
bx1111111100 5
0&
1'
#520000
0'
#525000
1'
#530000
0'
#535000
1'
#540000
0'
#545000
b101110 >
1'
#550000
0'
#555000
1&
1'
#560000
0'
#565000
0&
1'
#570000
0'
#575000
1'
#580000
0'
#585000
1'
#590000
0'
#595000
b101101 >
1'
#600000
0'
#605000
b10101 ,
b11111111111111111111111111111111 9
b10101 7
bx111 8
bx11111111000 5
1&
1'
#610000
0'
#615000
b101101 ,
b11111111111111111111111111111111 9
b101101 7
bx1111 8
bx111111110000 5
0&
1'
#620000
0'
#625000
1'
#630000
0'
#635000
1'
#640000
0'
#645000
b101100 >
1'
#650000
0'
#655000
1&
1'
#660000
0'
#665000
0&
1'
#670000
0'
#675000
1'
#680000
0'
#685000
1'
#690000
0'
#695000
b101011 >
1'
#700000
0'
#705000
b1011101 ,
b11111111111111111111111111111111 9
b1011101 7
bx11111 8
bx1111111100000 5
1&
1'
#710000
0'
#715000
b10111101 ,
b11111111111111111111111111111111 9
b10111101 7
bx111111 8
bx11111111000000 5
0&
1'
#720000
0'
#725000
1'
#730000
0'
#735000
1'
#740000
0'
#745000
b101010 >
1'
#750000
0'
#755000
1&
1'
#760000
0'
#765000
0&
1'
#770000
0'
#775000
1'
#780000
0'
#785000
1'
#790000
0'
#795000
b101001 >
1'
#800000
0'
#805000
b1111010 ,
b11111111111111111111111111111111 9
b1111010 7
bx1111111 8
bx111111110000000 5
1&
1'
#810000
0'
#815000
b11110011 ,
b11111111111111111111111111111111 9
b11110011 7
bx11111111 8
bx1111111100000000 5
0&
1'
#820000
0'
#825000
1'
#830000
0'
#835000
1'
#840000
0'
#845000
b101000 >
1'
#850000
0'
#855000
1&
1'
#860000
0'
#865000
0&
1'
#870000
0'
#875000
1'
#880000
0'
#885000
1'
#890000
0'
#895000
b100111 >
1'
#900000
0'
#905000
b11100001 ,
b11111111111111111111111111111111 9
b11100001 7
bx111111110 8
bx11111111000000000 5
1&
1'
#910000
0'
#915000
b11000101 ,
b11111111111111111111111111111111 9
b11000101 7
bx1111111100 8
bx111111110000000000 5
0&
1'
#920000
0'
#925000
1'
#930000
0'
#935000
1'
#940000
0'
#945000
b100110 >
1'
#950000
0'
#955000
1&
1'
#960000
0'
#965000
0&
1'
#970000
0'
#975000
1'
#980000
0'
#985000
1'
#990000
0'
#995000
b100101 >
1'
#1000000
0'
#1005000
b10001101 ,
b11111111111111111111111111111111 9
b10001101 7
bx11111111000 8
bx1111111100000000000 5
1&
1'
#1010000
0'
#1015000
b11101 ,
b11111111111111111111111111111111 9
b11101 7
bx111111110000 8
bx11111111000000000000 5
0&
1'
#1020000
0'
#1025000
1'
#1030000
0'
#1035000
1'
#1040000
0'
#1045000
b100100 >
1'
#1050000
0'
#1055000
1&
1%
1'
#1060000
0'
#1065000
0&
1'
#1070000
0'
#1075000
1'
#1080000
0'
#1085000
1'
#1090000
0'
#1095000
b100011 >
1'
#1100000
0'
#1105000
b111010 ,
b11111111111111111111111111111111 9
b111010 7
bx1111111100000 8
bx111111110000000000000 5
1&
0%
1'
#1110000
0'
#1115000
b1110100 ,
b11111111111111111111111111111111 9
b1110100 7
bx11111111000000 8
bx1111111100000000000000 5
0&
1'
#1120000
0'
#1125000
1'
#1130000
0'
#1135000
1'
#1140000
0'
#1145000
b100010 >
1'
#1150000
0'
#1155000
1&
1'
#1160000
0'
#1165000
0&
1'
#1170000
0'
#1175000
1'
#1180000
0'
#1185000
1'
#1190000
0'
#1195000
b100001 >
1'
#1200000
0'
#1205000
b11101000 ,
b11111111111111111111111111111111 9
b11101000 7
bx111111110000000 8
bx11111111000000000000001 5
1&
1%
1'
#1210000
0'
#1215000
b11010111 ,
b11111111111111111111111111111111 9
b11010111 7
bx1111111100000000 8
bx111111110000000000000011 5
0&
1'
#1220000
0'
#1225000
1'
#1230000
0'
#1235000
1'
#1240000
0'
#1245000
b100000 >
1'
#1250000
0'
#1255000
1&
0%
1'
#1260000
0'
#1265000
0&
1'
#1270000
0'
#1275000
1'
#1280000
0'
#1285000
1'
#1290000
0'
#1295000
b11111 >
1'
#1300000
0'
#1305000
b10101001 ,
b11111111111111111111111111111111 9
b10101001 7
bx11111111000000000 8
bx1111111100000000000000110 5
1&
1'
#1310000
0'
#1315000
b1010101 ,
b11111111111111111111111111111111 9
b1010101 7
bx111111110000000000 8
bx11111111000000000000001100 5
0&
1'
#1320000
0'
#1325000
1'
#1330000
0'
#1335000
1'
#1340000
0'
#1345000
b11110 >
1'
#1350000
0'
#1355000
1&
1'
#1360000
0'
#1365000
0&
1'
#1370000
0'
#1375000
1'
#1380000
0'
#1385000
1'
#1390000
0'
#1395000
b11101 >
1'
#1400000
0'
#1405000
b10101010 ,
b11111111111111111111111111111111 9
b10101010 7
bx1111111100000000000 8
bx111111110000000000000011001 5
1&
1%
1'
#1410000
0'
#1415000
b1010011 ,
b11111111111111111111111111111111 9
b1010011 7
bx11111111000000000000 8
bx1111111100000000000000110011 5
0&
1'
#1420000
0'
#1425000
1'
#1430000
0'
#1435000
1'
#1440000
0'
#1445000
b11100 >
1'
#1450000
0'
#1455000
1&
1'
#1460000
0'
#1465000
0&
1'
#1470000
0'
#1475000
1'
#1480000
0'
#1485000
1'
#1490000
0'
#1495000
b11011 >
1'
#1500000
0'
#1505000
b10100110 ,
b11111111111111111111111111111111 9
b10100110 7
bx111111110000000000000 8
bx11111111000000000000001100110 5
1&
0%
1'
#1510000
0'
#1515000
b1001011 ,
b11111111111111111111111111111111 9
b1001011 7
bx1111111100000000000000 8
bx111111110000000000000011001100 5
0&
1'
#1520000
0'
#1525000
1'
#1530000
0'
#1535000
1'
#1540000
0'
#1545000
b11010 >
1'
#1550000
0'
#1555000
1&
1%
1'
#1560000
0'
#1565000
0&
1'
#1570000
0'
#1575000
1'
#1580000
0'
#1585000
1'
#1590000
0'
#1595000
b11001 >
1'
#1600000
0'
#1605000
b10010001 ,
b11111111111111111111111111111111 9
b10010001 7
bx11111111000000000000001 8
bx1111111100000000000000110011000 5
1&
0%
1'
#1610000
0'
#1615000
b100010 ,
b11111111111111111111111111111111 9
b100010 7
bx111111110000000000000011 8
bx11111111000000000000001100110000 5
0&
1'
#1620000
0'
#1625000
1'
#1630000
0'
#1635000
1'
#1640000
0'
#1645000
b11000 >
1'
#1650000
0'
#1655000
1&
1'
#1660000
0'
#1665000
0&
1'
#1670000
0'
#1675000
1'
#1680000
0'
#1685000
1'
#1690000
0'
#1695000
b10111 >
1'
#1700000
0'
#1705000
b1000100 ,
b11111111111111111111111111111111 9
b1000100 7
bx1111111100000000000000110 8
bx111111110000000000000011001100000 5
1&
1'
#1710000
0'
#1715000
b10001000 ,
b11111111111111111111111111111111 9
b10001000 7
bx11111111000000000000001100 8
bx1111111100000000000000110011000000 5
0&
1'
#1720000
0'
#1725000
1'
#1730000
0'
#1735000
1'
#1740000
0'
#1745000
b10110 >
1'
#1750000
0'
#1755000
1&
1%
1'
#1760000
0'
#1765000
0&
1'
#1770000
0'
#1775000
1'
#1780000
0'
#1785000
1'
#1790000
0'
#1795000
b10101 >
1'
#1800000
0'
#1805000
b10000 ,
b11111111111111111111111111111111 9
b10000 7
bx111111110000000000000011001 8
bx11111111000000000000001100110000000 5
1&
0%
1'
#1810000
0'
#1815000
b100111 ,
b11111111111111111111111111111111 9
b100111 7
bx1111111100000000000000110011 8
bx111111110000000000000011001100000000 5
0&
1'
#1820000
0'
#1825000
1'
#1830000
0'
#1835000
1'
#1840000
0'
#1845000
b10100 >
1'
#1850000
0'
#1855000
1&
1%
1'
#1860000
0'
#1865000
0&
1'
#1870000
0'
#1875000
1'
#1880000
0'
#1885000
1'
#1890000
0'
#1895000
b10011 >
1'
#1900000
0'
#1905000
b1001110 ,
b11111111111111111111111111111111 9
b1001110 7
bx11111111000000000000001100110 8
bx1111111100000000000000110011000000000 5
1&
0%
1'
#1910000
0'
#1915000
b10011100 ,
b11111111111111111111111111111111 9
b10011100 7
bx111111110000000000000011001100 8
bx11111111000000000000001100110000000000 5
0&
1'
#1920000
0'
#1925000
1'
#1930000
0'
#1935000
1'
#1940000
0'
#1945000
b10010 >
1'
#1950000
0'
#1955000
1&
1%
1'
#1960000
0'
#1965000
0&
1'
#1970000
0'
#1975000
1'
#1980000
0'
#1985000
1'
#1990000
0'
#1995000
b10001 >
1'
#2000000
0'
#2005000
b111111 ,
b11111111111111111111111111111111 9
b111111 7
bx1111111100000000000000110011000 8
bx111111110000000000000011001100000000001 5
1&
1'
#2010000
0'
#2015000
b1111110 ,
b11111111111111111111111111111111 9
b1111110 7
bx11111111000000000000001100110000 8
bx1111111100000000000000110011000000000011 5
0&
1'
#2020000
0'
#2025000
1'
#2030000
0'
#2035000
1'
#2040000
0'
#2045000
b10000 >
1'
#2050000
0'
#2055000
1&
0%
1'
#2060000
0'
#2065000
0&
1'
#2070000
0'
#2075000
1'
#2080000
0'
#2085000
1'
#2090000
0'
#2095000
b1111 >
1'
#2100000
0'
#2105000
b11111100 ,
b11111111111111111111111111111111 9
b11111100 7
bx111111110000000000000011001100000 8
bx11111111000000000000001100110000000000110 5
1&
1'
#2110000
0'
#2115000
b11111111 ,
b11111111111111111111111111111111 9
b11111111 7
bx1111111100000000000000110011000000 8
bx111111110000000000000011001100000000001100 5
0&
1'
#2120000
0'
#2125000
1'
#2130000
0'
#2135000
1'
#2140000
0'
#2145000
b1110 >
1'
#2150000
0'
#2155000
1&
1%
1'
#2160000
0'
#2165000
0&
1'
#2170000
0'
#2175000
1'
#2180000
0'
#2185000
1'
#2190000
0'
#2195000
b1101 >
1'
#2200000
0'
#2205000
b11111001 ,
b11111111111111111111111111111111 9
b11111001 7
bx11111111000000000000001100110000000 8
bx1111111100000000000000110011000000000011001 5
1&
1'
#2210000
0'
#2215000
b11110101 ,
b11111111111111111111111111111111 9
b11110101 7
bx111111110000000000000011001100000000 8
bx11111111000000000000001100110000000000110011 5
0&
1'
#2220000
0'
#2225000
1'
#2230000
0'
#2235000
1'
#2240000
0'
#2245000
b1100 >
1'
#2250000
0'
#2255000
1&
1'
#2260000
0'
#2265000
0&
1'
#2270000
0'
#2275000
1'
#2280000
0'
#2285000
1'
#2290000
0'
#2295000
b1011 >
1'
#2300000
0'
#2305000
b11101101 ,
b11111111111111111111111111111111 9
b11101101 7
bx1111111100000000000000110011000000000 8
bx111111110000000000000011001100000000001100111 5
1&
1'
#2310000
0'
#2315000
b11011101 ,
b11111111111111111111111111111111 9
b11011101 7
bx11111111000000000000001100110000000000 8
bx1111111100000000000000110011000000000011001111 5
0&
1'
#2320000
0'
#2325000
1'
#2330000
0'
#2335000
1'
#2340000
0'
#2345000
b1010 >
1'
#2350000
0'
#2355000
1&
0%
1'
#2360000
0'
#2365000
0&
1'
#2370000
0'
#2375000
1'
#2380000
0'
#2385000
1'
#2390000
0'
#2395000
b1001 >
1'
#2400000
0'
#2405000
b10111010 ,
b11111111111111111111111111111111 9
b10111010 7
bx111111110000000000000011001100000000001 8
bx11111111000000000000001100110000000000110011110 5
1&
1'
#2410000
0'
#2415000
b1110100 ,
b11111111111111111111111111111111 9
b1110100 7
bx1111111100000000000000110011000000000011 8
bx111111110000000000000011001100000000001100111100 5
0&
1'
#2420000
0'
#2425000
1'
#2430000
0'
#2435000
1'
#2440000
0'
#2445000
b1000 >
1'
#2450000
0'
#2455000
1&
1'
#2460000
0'
#2465000
0&
1'
#2470000
0'
#2475000
1'
#2480000
0'
#2485000
1'
#2490000
0'
#2495000
b111 >
1'
#2500000
0'
#2505000
b11101000 ,
b11111111111111111111111111111111 9
b11101000 7
bx11111111000000000000001100110000000000110 8
bx1111111100000000000000110011000000000011001111001 5
1&
1%
1'
#2510000
0'
#2515000
b11010111 ,
b11111111111111111111111111111111 9
b11010111 7
bx111111110000000000000011001100000000001100 8
bx11111111000000000000001100110000000000110011110011 5
0&
1'
#2520000
0'
#2525000
1'
#2530000
0'
#2535000
1'
#2540000
0'
#2545000
b110 >
1'
#2550000
0'
#2555000
1&
1'
#2560000
0'
#2565000
0&
1'
#2570000
0'
#2575000
1'
#2580000
0'
#2585000
1'
#2590000
0'
#2595000
b101 >
1'
#2600000
0'
#2605000
b10101110 ,
b11111111111111111111111111111111 9
b10101110 7
bx1111111100000000000000110011000000000011001 8
bx111111110000000000000011001100000000001100111100110 5
1&
0%
1'
#2610000
0'
#2615000
b1011100 ,
b11111111111111111111111111111111 9
b1011100 7
bx11111111000000000000001100110000000000110011 8
bx1111111100000000000000110011000000000011001111001100 5
0&
1'
#2620000
0'
#2625000
1'
#2630000
0'
#2635000
1'
#2640000
0'
#2645000
b100 >
1'
#2650000
0'
#2655000
1&
1%
1'
#2660000
0'
#2665000
0&
1'
#2670000
0'
#2675000
1'
#2680000
0'
#2685000
1'
#2690000
0'
#2695000
b11 >
1'
#2700000
0'
#2705000
b10111111 ,
b11111111111111111111111111111111 9
b10111111 7
bx111111110000000000000011001100000000001100111 8
bx11111111000000000000001100110000000000110011110011000 5
1&
0%
1'
#2710000
0'
#2715000
b1111110 ,
b11111111111111111111111111111111 9
b1111110 7
bx1111111100000000000000110011000000000011001111 8
bx111111110000000000000011001100000000001100111100110000 5
0&
1'
#2720000
0'
#2725000
1'
#2730000
0'
#2735000
1'
#2740000
0'
#2745000
b10 >
1'
#2750000
0'
#2755000
1&
1%
1'
#2760000
0'
#2765000
0&
1'
#2770000
0'
#2775000
1'
#2780000
0'
#2785000
1'
#2790000
0'
#2795000
b1 >
1'
#2800000
0'
#2805000
b11111100 ,
b11111111111111111111111111111111 9
b11111100 7
bx11111111000000000000001100110000000000110011110 8
bx1111111100000000000000110011000000000011001111001100001 5
1&
1'
#2810000
0'
#2815000
b11111111 ,
b11111111111111111111111111111111 9
b11111111 7
b111111110000000000000011001100000000001100111100 8
b11111111000000000000001100110000000000110011110011000011 5
0&
1'
#2820000
0'
#2825000
1'
#2830000
0'
#2835000
1'
#2840000
0'
#2845000
b0 >
1'
#2850000
0'
#2855000
1&
0%
1'
#2860000
0'
#2865000
0&
1'
#2870000
0'
#2875000
1'
#2880000
0'
#2885000
1'
#2890000
0'
#2895000
b1111101 ;
b11111111111111111111111111111111 +
b1111101 )
b101010100000000110000111011001010100001100100001 *
b10101010000000011000011101100101010000110010000101111101 =
b10000111011001010100001100100001 <
b1 :
b110111 >
1'
#2900000
0'
#2905000
b100001 ,
b11111111111111111111111111111111 9
b100001 7
b111111100000000000000110011000000000011001111001 8
b11111110000000000000011001100000000001100111100110000111 5
1&
1%
1'
#2910000
0'
#2915000
b10011010 ,
b11111111111111111111111111111111 9
b10011010 7
b111111000000000000001100110000000000110011110011 8
b11111100000000000000110011000000000011001111001100001111 5
0&
1'
#2920000
0'
#2925000
1'
#2930000
0'
#2935000
1'
#2940000
0'
#2945000
b110110 >
1'
#2950000
0'
#2955000
1&
0%
1'
#2960000
0'
#2965000
0&
1'
#2970000
0'
#2975000
1'
#2980000
0'
#2985000
1'
#2990000
0'
#2995000
b110101 >
1'
#3000000
0'
#3005000
b11101100 ,
b11111111111111111111111111111111 9
b11101100 7
b111110000000000000011001100000000001100111100110 8
b11111000000000000001100110000000000110011110011000011111 5
1&
1%
1'
#3010000
0'
#3015000
b0 ,
b11111111111111111111111111111111 9
b0 7
b111100000000000000110011000000000011001111001100 8
b11110000000000000011001100000000001100111100110000111111 5
0&
1'
#3020000
0'
#3025000
1'
#3030000
0'
#3035000
1'
#3040000
0'
#3045000
b110100 >
1'
#3050000
0'
#3055000
1&
0%
1'
#3060000
0'
#3065000
0&
1'
#3070000
0'
#3075000
1'
#3080000
0'
#3085000
1'
#3090000
0'
#3095000
b110011 >
1'
#3100000
0'
#3105000
b11011111 ,
b11011111 7
b11111111111111111111111111111111 9
b111000000000000001100110000000000110011110011000 8
b11100000000000000110011000000000011001111001100001111111 5
1&
1%
1'
#3110000
0'
#3115000
b1100110 ,
b11111111111111111111111111111111 9
b1100110 7
b110000000000000011001100000000001100111100110000 8
b11000000000000001100110000000000110011110011000011111111 5
0&
1'
#3120000
0'
#3125000
1'
#3130000
0'
#3135000
1'
#3140000
0'
#3145000
b110010 >
1'
#3150000
0'
#3155000
1&
0%
1'
#3160000
0'
#3165000
0&
1'
#3170000
0'
#3175000
1'
#3180000
0'
#3185000
1'
#3190000
0'
#3195000
b110001 >
1'
#3200000
0'
#3205000
b10100 ,
b11111111111111111111111111111111 9
b10100 7
b100000000000000110011000000000011001111001100001 8
b10000000000000011001100000000001100111100110000111111111 5
1&
1%
1'
#3210000
0'
#3215000
b11110000 ,
b11111111111111111111111111111111 9
b11110000 7
b1100110000000000110011110011000011 8
b110011000000000011001111001100001111111111 5
0&
1'
#3220000
0'
#3225000
1'
#3230000
0'
#3235000
1'
#3240000
0'
#3245000
b110000 >
1'
#3250000
0'
#3255000
1&
0%
1'
#3260000
0'
#3265000
0&
1'
#3270000
0'
#3275000
1'
#3280000
0'
#3285000
1'
#3290000
0'
#3295000
b101111 >
1'
#3300000
0'
#3305000
b11100000 ,
b11111111111111111111111111111111 9
b11100000 7
b11001100000000001100111100110000111 8
b1100110000000000110011110011000011111111110 5
1&
1'
#3310000
0'
#3315000
b11000000 ,
b11111111111111111111111111111111 9
b11000000 7
b110011000000000011001111001100001111 8
b11001100000000001100111100110000111111111100 5
0&
1'
#3320000
0'
#3325000
1'
#3330000
0'
#3335000
1'
#3340000
0'
#3345000
b101110 >
1'
#3350000
0'
#3355000
1&
1'
#3360000
0'
#3365000
0&
1'
#3370000
0'
#3375000
1'
#3380000
0'
#3385000
1'
#3390000
0'
#3395000
b101101 >
1'
#3400000
0'
#3405000
b10000000 ,
b11111111111111111111111111111111 9
b10000000 7
b1100110000000000110011110011000011111 8
b110011000000000011001111001100001111111111000 5
1&
1'
#3410000
0'
#3415000
b0 ,
b11111111111111111111111111111111 9
b0 7
b11001100000000001100111100110000111111 8
b1100110000000000110011110011000011111111110000 5
0&
1'
#3420000
0'
#3425000
1'
#3430000
0'
#3435000
1'
#3440000
0'
#3445000
b101100 >
1'
#3450000
0'
#3455000
1&
1'
#3460000
0'
#3465000
0&
1'
#3470000
0'
#3475000
1'
#3480000
0'
#3485000
1'
#3490000
0'
#3495000
b101011 >
1'
#3500000
0'
#3505000
b111 ,
b111 7
b11111111111111111111111111111111 9
b110011000000000011001111001100001111111 8
b11001100000000001100111100110000111111111100000 5
1&
1'
#3510000
0'
