async_fifo_generic.v
// ============================================================================
// Asynchronous FIFO - 200MHz to 100MHz Clock Domain Crossing
// ============================================================================
// Clock domains:
//   - Write: clk_wr (200MHz) - CDR output data
//   - Read:  clk_rd (100MHz) - System processing
//
// Parameters:
//   - DATA_WIDTH: 32 bits (RHS2116 data width)
//   - ADDR_WIDTH: 4 (16-depth, enough for CDR buffering)
//
// Safety features:
//   - Gray code pointer synchronization
//   - Double flip-flop sync chain with ASYNC_REG protection
//   - Full/Empty flags with safe Gray code comparison
// ============================================================================

module async_fifo_generic #(
    parameter DATA_WIDTH = 32,
    parameter ADDR_WIDTH = 4
)(
    // Write port - 200MHz domain (CDR output)
    input  wire                     clk_wr,
    input  wire                     rst_wr_n,
    input  wire [DATA_WIDTH-1:0]    din,
    input  wire                     wr_en,
    output wire                     full,
    output wire                     almost_full,

    // Read port - 100MHz domain (System logic)
    input  wire                     clk_rd,
    input  wire                     rst_rd_n,
    output wire [DATA_WIDTH-1:0]    dout,
    input  wire                     rd_en,
    output wire                     empty,
    output wire                     valid
);

    // ========================================================================
    // Parameters
    // ========================================================================
    localparam PTR_WIDTH = ADDR_WIDTH + 1;      // Extra bit for full/empty
    localparam FIFO_DEPTH = (1 << ADDR_WIDTH);  // 16 entries
    localparam ALMOST_FULL_THRESHOLD = FIFO_DEPTH - 2;  // 14/16

    // ========================================================================
    // Memory array
    // ========================================================================
    reg [DATA_WIDTH-1:0] mem [0:FIFO_DEPTH-1];

    // ========================================================================
    // Write domain - Binary and Gray pointers
    // ========================================================================
    reg [PTR_WIDTH-1:0] wr_ptr_bin;
    reg [PTR_WIDTH-1:0] wr_ptr_gray;

    wire [PTR_WIDTH-1:0] wr_ptr_bin_next = wr_ptr_bin + ((wr_en && !full) ? 1'b1 : 1'b0);
    wire [PTR_WIDTH-1:0] wr_ptr_gray_next = (wr_ptr_bin_next >> 1) ^ wr_ptr_bin_next;

    always @(posedge clk_wr or negedge rst_wr_n) begin
        if (!rst_wr_n) begin
            wr_ptr_bin  <= {PTR_WIDTH{1'b0}};
            wr_ptr_gray <= {PTR_WIDTH{1'b0}};
            $display("FIFO Reset active at %t", $time);
        end else begin
            wr_ptr_bin  <= wr_ptr_bin_next;
            wr_ptr_gray <= wr_ptr_gray_next;

            // Write to memory
            if (wr_en && !full) begin
                mem[wr_ptr_bin[ADDR_WIDTH-1:0]] <= din;
                $display("FIFO Write: %h (ptr: %d)", din, wr_ptr_bin);
            end else if (wr_en && full) begin
                $display("FIFO Write Dropped: Full!");
            end
            // Unconditional debug
            $display("FIFO Clock: %t, wr_en: %b, full: %b, rst_wr_n: %b", $time, wr_en, full, rst_wr_n);
             if (wr_en === 1'bx) $display("FIFO WARNING: wr_en is X at %t", $time);
        end
    end

    // ========================================================================
    // Read domain - Binary and Gray pointers
    // ========================================================================
    reg [PTR_WIDTH-1:0] rd_ptr_bin;
    reg [PTR_WIDTH-1:0] rd_ptr_gray;
    reg [DATA_WIDTH-1:0] rd_data_reg;
    reg rd_valid_reg;

    wire [PTR_WIDTH-1:0] rd_ptr_bin_next = rd_ptr_bin + ((rd_en && !empty) ? 1'b1 : 1'b0);
    wire [PTR_WIDTH-1:0] rd_ptr_gray_next = (rd_ptr_bin_next >> 1) ^ rd_ptr_bin_next;

    always @(posedge clk_rd or negedge rst_rd_n) begin
        if (!rst_rd_n) begin
            rd_ptr_bin   <= {PTR_WIDTH{1'b0}};
            rd_ptr_gray  <= {PTR_WIDTH{1'b0}};
            rd_data_reg  <= {DATA_WIDTH{1'b0}};
            rd_valid_reg <= 1'b0;
        end else begin
            rd_ptr_bin   <= rd_ptr_bin_next;
            rd_ptr_gray  <= rd_ptr_gray_next;

            // Read from memory
            if (rd_en && !empty) begin
                rd_data_reg <= mem[rd_ptr_bin[ADDR_WIDTH-1:0]];
                rd_valid_reg <= 1'b1;
                $display("FIFO Read: %h (ptr: %d)", mem[rd_ptr_bin[ADDR_WIDTH-1:0]], rd_ptr_bin);
            end else begin
                rd_valid_reg <= 1'b0;
            end
        end
    end

    // ========================================================================
    // CDC: Gray pointer synchronization with double flip-flop chain
    // ========================================================================

    // Read pointer Gray -> Write domain sync
    reg [PTR_WIDTH-1:0] rd_gray_wr1 /* synthesis altera_attribute = "-name ASYNC_REG ON" */;
    reg [PTR_WIDTH-1:0] rd_gray_wr2 /* synthesis altera_attribute = "-name ASYNC_REG ON" */;

    always @(posedge clk_wr or negedge rst_wr_n) begin
        if (!rst_wr_n) begin
            rd_gray_wr1 <= {PTR_WIDTH{1'b0}};
            rd_gray_wr2 <= {PTR_WIDTH{1'b0}};
        end else begin
            rd_gray_wr1 <= rd_ptr_gray;
            rd_gray_wr2 <= rd_gray_wr1;
        end
    end

    // Write pointer Gray -> Read domain sync
    reg [PTR_WIDTH-1:0] wr_gray_rd1 /* synthesis altera_attribute = "-name ASYNC_REG ON" */;
    reg [PTR_WIDTH-1:0] wr_gray_rd2 /* synthesis altera_attribute = "-name ASYNC_REG ON" */;

    always @(posedge clk_rd or negedge rst_rd_n) begin
        if (!rst_rd_n) begin
            wr_gray_rd1 <= {PTR_WIDTH{1'b0}};
            wr_gray_rd2 <= {PTR_WIDTH{1'b0}};
        end else begin
            wr_gray_rd1 <= wr_ptr_gray;
            wr_gray_rd2 <= wr_gray_rd1;
        end
    end

    // ========================================================================
    // Full/Empty flag generation
    // ========================================================================

    // Empty: read pointer == synchronized write pointer
    assign empty = (rd_ptr_gray == wr_gray_rd2);

    // Full: write pointer + 1 == synchronized read pointer (top bits differ)
    assign full = (wr_ptr_gray_next == {~wr_gray_rd2[PTR_WIDTH-1:PTR_WIDTH-2],
                                         wr_gray_rd2[PTR_WIDTH-3:0]});

    // Almost full: threshold-based for flow control
    // Gray to Binary conversion for rd_gray_wr2
    reg [PTR_WIDTH-1:0] rd_ptr_bin_wr;
    integer i;
    always @(*) begin
        rd_ptr_bin_wr[PTR_WIDTH-1] = rd_gray_wr2[PTR_WIDTH-1];
        for (i = PTR_WIDTH-2; i >= 0; i = i - 1) begin
            rd_ptr_bin_wr[i] = rd_ptr_bin_wr[i+1] ^ rd_gray_wr2[i];
        end
    end

    // Almost full: threshold-based for flow control
    wire [PTR_WIDTH-1:0] used_words_wr = wr_ptr_bin - rd_ptr_bin_wr;
    assign almost_full = (used_words_wr >= ALMOST_FULL_THRESHOLD[PTR_WIDTH-1:0]);

    // ========================================================================
    // Outputs
    // ========================================================================
    assign dout  = rd_data_reg;
    assign valid = rd_valid_reg;

endmodule

frame_packer_100m.v
// ============================================================================
// Frame Packer - 100MHz with Async FIFO
// ============================================================================
// Packs 32-bit data into 56-bit frames: {SYNC(8), CNT(8), DATA(32), CRC(8)}
// Handles clk_spi (64MHz) -> clk_sys (100MHz) CDC internally
//
// Data flow:
//   din (clk_spi) → Async FIFO → Frame assembly → Bit serialization
//
// Frame rate: 446.4k frames/sec (matches SPI rate)
// Bit rate: 25 Mbps (data) → 50 Mbps Manchester line rate
// ============================================================================

module frame_packer_100m (
    // Clocks
    input wire clk_spi,      // 64MHz SPI clock (write side)
    input wire clk_sys,      // 100MHz system clock (read side)
    input wire rst_n,

    // Input from SPI Master (clk_spi domain)
    input  wire [31:0] din,
    input  wire        din_valid,

    // Serial output (clk_sys domain)
    output reg         tx_bit,
    output reg         tx_bit_valid,
    input  wire        tx_bit_ready,

    // Status
    output wire [7:0]  frame_count
);

    always @(posedge clk_spi) begin
        // if (din_valid) $display("Frame Packer: din_valid asserted, din=%h", din);
        $display("FP Time: %t, din_valid: %b, din: %h", $time, din_valid, din);
    end

    // ========================================================================
    // Frame format: {SYNC(8), CNT(8), DATA(32), CRC(8)}
    // ========================================================================
    localparam SYNC_BYTE = 8'hAA;
    localparam CRC_POLY  = 8'h07;  // x^8 + x^2 + x + 1

    // ========================================================================
    // Async FIFO (SPI domain -> System domain)
    // ========================================================================
    wire [31:0] fifo_dout;
    wire        fifo_empty;
    wire        fifo_full;
    reg         fifo_rd_en;

    async_fifo_generic #(
        .DATA_WIDTH(32),
        .ADDR_WIDTH(4)  // 16 entries
    ) u_async_fifo (
        .clk_wr      (clk_spi),
        .rst_wr_n    (rst_n),
        .din         (din),
        .wr_en       (din_valid),
        .full        (fifo_full),
        .almost_full (),  // Not used

        .clk_rd      (clk_sys),
        .rst_rd_n    (rst_n),
        .dout        (fifo_dout),
        .rd_en       (fifo_rd_en),
        .empty       (fifo_empty),
        .valid       ()
    );

    // ========================================================================
    // Frame assembly and serialization
    // ========================================================================
    reg [7:0]   frame_cnt;      // 8-bit frame counter
    reg [55:0]  shift_reg;      // Frame shift register
    reg [5:0]   bit_cnt;        // 0-55 (56 bits)
    reg         sending;        // Frame transmission in progress

    wire [31:0] convert_data = fifo_dout;
    wire [7:0]  convert_crc  = calc_crc8(convert_data, frame_cnt);

    function [7:0] calc_crc8;
        input [31:0] data;
        input [7:0]  cnt;
        integer i;
        reg [7:0] crc;
        reg [47:0] msg;
        begin
            msg = {SYNC_BYTE, cnt, data};
            crc = 8'h00;
            for (i = 47; i >= 0; i = i - 1) begin
                if ((crc[7] ^ msg[i]) == 1'b1)
                    crc = {crc[6:0], 1'b0} ^ 8'h07;
                else
                    crc = {crc[6:0], 1'b0};
            end
            calc_crc8 = crc;
        end
    endfunction

    // ========================================================================
    // State machine: IDLE -> LOAD -> SEND
    // ========================================================================
    localparam IDLE = 2'b00;
    localparam LOAD = 2'b01;
    localparam SEND = 2'b10;

    reg [1:0] state;

    always @(posedge clk_sys or negedge rst_n) begin
        if (!rst_n) begin
            state       <= IDLE;
            frame_cnt   <= 8'b0;
            shift_reg   <= 56'b0;
            bit_cnt     <= 6'b0;
            sending     <= 1'b0;
            tx_bit      <= 1'b0;
            tx_bit_valid <= 1'b0;
            fifo_rd_en  <= 1'b0;
        end else begin
            tx_bit_valid <= 1'b0;  // Default
            fifo_rd_en   <= 1'b0;

            case (state)
                IDLE: begin
                    if (!fifo_empty && tx_bit_ready) begin
                        state      <= LOAD;
                        fifo_rd_en <= 1'b1;
                    end
                end

                LOAD: begin
                    // Assemble frame: {SYNC, CNT, DATA, CRC}
                    shift_reg <= {
                        SYNC_BYTE,
                        frame_cnt,
                        convert_data,
                        convert_crc
                    };

                    frame_cnt <= frame_cnt + 8'b1;
                    bit_cnt   <= 6'b0;
                    sending   <= 1'b1;
                    state     <= SEND;
                    $display("Frame Packer: Sending frame %h, data %h, crc %h", frame_cnt, convert_data, convert_crc);
                end

                SEND: begin
                    if (tx_bit_ready) begin
                        tx_bit       <= shift_reg[55];        // MSB first
                        tx_bit_valid <= 1'b1;
                        shift_reg    <= {shift_reg[54:0], 1'b0}; // Shift left
                        bit_cnt      <= bit_cnt + 1'b1;

                        if (bit_cnt == 6'b110111) begin  // All 56 bits sent
                            sending <= 1'b0;
                            state   <= IDLE;
                        end
                    end
                end

                default: state <= IDLE;
            endcase
        end
    end

    // ========================================================================
    // Status outputs
    // ========================================================================
    assign frame_count = frame_cnt;

endmodule

testbench/tb_frame_packer.v
`timescale 1ns / 1ps

module tb_frame_packer;

    reg clk_spi;
    reg clk_sys;
    reg rst_n;
    reg [31:0] din;
    reg din_valid;
    wire tx_bit;
    wire tx_bit_valid;
    reg tx_bit_ready;
    wire [7:0] frame_count;

    // Clock generation
    initial begin
        clk_spi = 0;
        forever #7.8125 clk_spi = ~clk_spi;
    end

    initial begin
        clk_sys = 0;
        forever #5 clk_sys = ~clk_sys;
    end

    // DUT
    frame_packer_100m u_dut (
        .clk_spi(clk_spi),
        .clk_sys(clk_sys),
        .rst_n(rst_n),
        .din(din),
        .din_valid(din_valid),
        .tx_bit(tx_bit),
        .tx_bit_valid(tx_bit_valid),
        .tx_bit_ready(tx_bit_ready),
        .frame_count(frame_count)
    );

    initial begin
        $dumpfile("tb_frame_packer.vcd");
        $dumpvars(0, tb_frame_packer);

        rst_n = 0;
        din = 0;
        din_valid = 0;
        tx_bit_ready = 0;

        #100;
        rst_n = 1;
        
        // Write to FIFO
        @(posedge clk_spi);
        din = 32'hAABBCCDD;
        din_valid = 1;
        @(posedge clk_spi);
        din_valid = 0;

        // Enable reading
        #100;
        tx_bit_ready = 1;

        // Wait for frame transmission
        repeat(56) @(posedge clk_sys);
        
        #1000;
        $finish;
    end

endmodule

testbench/tb_frame_packer.vcd
$date
	Thu Nov 20 16:27:12 2025
$end
$version
	Icarus Verilog
$end
$timescale
	1ps
$end
$scope module tb_frame_packer $end
$var wire 1 ! tx_bit_valid $end
$var wire 1 " tx_bit $end
$var wire 8 # frame_count [7:0] $end
$var reg 1 $ clk_spi $end
$var reg 1 % clk_sys $end
$var reg 32 & din [31:0] $end
$var reg 1 ' din_valid $end
$var reg 1 ( rst_n $end
$var reg 1 ) tx_bit_ready $end
$scope module u_dut $end
$var wire 1 $ clk_spi $end
$var wire 1 % clk_sys $end
$var wire 32 * convert_data [31:0] $end
$var wire 32 + din [31:0] $end
$var wire 1 ' din_valid $end
$var wire 8 , frame_count [7:0] $end
$var wire 1 ( rst_n $end
$var wire 1 ) tx_bit_ready $end
$var wire 1 - fifo_full $end
$var wire 1 . fifo_empty $end
$var wire 32 / fifo_dout [31:0] $end
$var wire 8 0 convert_crc [7:0] $end
$var parameter 8 1 CRC_POLY $end
$var parameter 2 2 IDLE $end
$var parameter 2 3 LOAD $end
$var parameter 2 4 SEND $end
$var parameter 8 5 SYNC_BYTE $end
$var reg 6 6 bit_cnt [5:0] $end
$var reg 1 7 fifo_rd_en $end
$var reg 8 8 frame_cnt [7:0] $end
$var reg 1 9 sending $end
$var reg 56 : shift_reg [55:0] $end
$var reg 2 ; state [1:0] $end
$var reg 1 " tx_bit $end
$var reg 1 ! tx_bit_valid $end
$scope function calc_crc8 $end
$var reg 8 < cnt [7:0] $end
$var reg 8 = crc [7:0] $end
$var reg 32 > data [31:0] $end
$var reg 48 ? msg [47:0] $end
$var integer 32 @ i [31:0] $end
$upscope $end
$scope module u_async_fifo $end
$var wire 1 % clk_rd $end
$var wire 1 $ clk_wr $end
$var wire 32 A din [31:0] $end
$var wire 1 7 rd_en $end
$var wire 5 B rd_ptr_gray_next [4:0] $end
$var wire 1 ( rst_rd_n $end
$var wire 1 ( rst_wr_n $end
$var wire 1 C valid $end
$var wire 1 ' wr_en $end
$var wire 5 D wr_ptr_gray_next [4:0] $end
$var wire 5 E wr_ptr_bin_next [4:0] $end
$var wire 5 F used_words_wr [4:0] $end
$var wire 5 G rd_ptr_bin_next [4:0] $end
$var wire 1 - full $end
$var wire 1 . empty $end
$var wire 32 H dout [31:0] $end
$var wire 1 I almost_full $end
$var parameter 32 J ADDR_WIDTH $end
$var parameter 37 K ALMOST_FULL_THRESHOLD $end
$var parameter 32 L DATA_WIDTH $end
$var parameter 36 M FIFO_DEPTH $end
$var parameter 33 N PTR_WIDTH $end
$var reg 32 O rd_data_reg [31:0] $end
$var reg 5 P rd_gray_wr1 [4:0] $end
$var reg 5 Q rd_gray_wr2 [4:0] $end
$var reg 5 R rd_ptr_bin [4:0] $end
$var reg 5 S rd_ptr_bin_wr [4:0] $end
$var reg 5 T rd_ptr_gray [4:0] $end
$var reg 1 U rd_valid_reg $end
$var reg 5 V wr_gray_rd1 [4:0] $end
$var reg 5 W wr_gray_rd2 [4:0] $end
$var reg 5 X wr_ptr_bin [4:0] $end
$var reg 5 Y wr_ptr_gray [4:0] $end
$var integer 32 Z i [31:0] $end
$upscope $end
$upscope $end
$upscope $end
$enddefinitions $end
$comment Show the parameter values. $end
$dumpall
b101 N
b10000 M
b100000 L
b1110 K
b100 J
b10101010 5
b10 4
b1 3
b0 2
b111 1
$end
#0
$dumpvars
b11111111111111111111111111111111 Z
b0 Y
b0 X
b0 W
b0 V
0U
b0 T
b0 S
b0 R
b0 Q
b0 P
b0 O
0I
b0 H
b0 G
b0 F
b0 E
b0 D
0C
b0 B
b0 A
b11111111111111111111111111111111 @
b101010100000000000000000000000000000000000000000 ?
b0 >
b11001010 =
b0 <
b0 ;
b0 :
09
b0 8
07
b0 6
b11001010 0
b0 /
1.
0-
b0 ,
b0 +
b0 *
0)
0(
0'
b0 &
0%
0$
b0 #
0"
0!
$end
#5000
1%
#7813
1$
#10000
0%
#15000
1%
#15626
0$
#20000
0%
#23439
1$
#25000
1%
#30000
0%
#31252
0$
#35000
1%
#39065
1$
#40000
0%
#45000
1%
#46878
0$
#50000
0%
#54691
1$
#55000
1%
#60000
0%
#62504
0$
#65000
1%
#70000
0%
#70317
1$
#75000
1%
#78130
0$
#80000
0%
#85000
1%
#85943
1$
#90000
0%
#93756
0$
#95000
1%
#100000
0%
1(
#101569
b1 D
b1 E
1'
b10101010101110111100110011011101 &
b10101010101110111100110011011101 +
b10101010101110111100110011011101 A
1$
#105000
1%
#109382
0$
#110000
0%
#115000
1%
#117195
b1 Y
b1 F
b1 X
b1 D
b1 E
0'
1$
#120000
0%
#125000
b1 V
1%
#125008
0$
#130000
0%
#132821
1$
#135000
0.
b1 W
1%
#140000
0%
#140634
0$
#145000
1%
#148447
1$
#150000
0%
#155000
1%
#156260
0$
#160000
0%
#164073
1$
#165000
1%
#170000
0%
#171886
0$
#175000
1%
#179699
1$
#180000
0%
#185000
1%
#187512
0$
#190000
0%
#195000
1%
#195325
1$
#200000
0%
#203138
0$
#205000
1%
#210000
0%
#210951
1$
#215000
1%
#217195
1)
#218764
0$
#220000
0%
#225000
b1 B
b1 G
17
b1 ;
1%
#226577
1$
#230000
0%
#234390
0$
#235000
b1 B
b11000001 0
b11111111111111111111111111111111 @
b11000001 =
b101010100000000110101010101110111100110011011101 ?
b1 <
b10101010101110111100110011011101 >
1C
1U
b10101010101110111100110011011101 *
b10101010101110111100110011011101 /
b10101010101110111100110011011101 H
b10101010101110111100110011011101 O
1.
b1 T
b1 G
b1 R
b10 ;
19
b1 #
b1 ,
b1 8
b10101010000000000000000000000000000000000000000011001010 :
07
1%
#240000
0%
#242203
b1 P
1$
#245000
b1 6
b1010100000000000000000000000000000000000000000110010100 :
1!
1"
0C
0U
1%
#250000
0%
#250016
0$
#255000
b10 6
b10101000000000000000000000000000000000000000001100101000 :
0"
1!
1%
#257829
b0 F
b1 S
b11111111111111111111111111111111 Z
b1 Q
1$
#260000
0%
#265000
b11 6
b1010000000000000000000000000000000000000000011001010000 :
1"
1!
1%
#265642
0$
#270000
0%
#273455
1$
#275000
b100 6
b10100000000000000000000000000000000000000000110010100000 :
0"
1!
1%
#280000
0%
#281268
0$
#285000
b101 6
b1000000000000000000000000000000000000000001100101000000 :
1"
1!
1%
#289081
1$
#290000
0%
#295000
b110 6
b10000000000000000000000000000000000000000011001010000000 :
0"
1!
1%
#296894
0$
#300000
0%
#304707
1$
#305000
b111 6
b110010100000000 :
1"
1!
1%
#310000
0%
#312520
0$
#315000
b1000 6
b1100101000000000 :
0"
1!
1%
#320000
0%
#320333
1$
#325000
b1001 6
b11001010000000000 :
1!
1%
#328146
0$
#330000
0%
#335000
b1010 6
b110010100000000000 :
1!
1%
#335959
1$
#340000
0%
#343772
0$
#345000
b1011 6
b1100101000000000000 :
1!
1%
#350000
0%
#351585
1$
#355000
b1100 6
b11001010000000000000 :
1!
1%
#359398
0$
#360000
0%
#365000
b1101 6
b110010100000000000000 :
1!
1%
#367211
1$
#370000
0%
#375000
b1110 6
b1100101000000000000000 :
1!
1%
#375024
0$
#380000
0%
#382837
1$
#385000
b1111 6
b11001010000000000000000 :
1!
1%
#390000
0%
#390650
0$
#395000
b10000 6
b110010100000000000000000 :
1!
1%
#398463
1$
#400000
0%
#405000
b10001 6
b1100101000000000000000000 :
1!
1%
#406276
0$
#410000
0%
#414089
1$
#415000
b10010 6
b11001010000000000000000000 :
1!
1%
#420000
0%
#421902
0$
#425000
b10011 6
b110010100000000000000000000 :
1!
1%
#429715
1$
#430000
0%
#435000
b10100 6
b1100101000000000000000000000 :
1!
1%
#437528
0$
#440000
0%
#445000
b10101 6
b11001010000000000000000000000 :
1!
1%
#445341
1$
#450000
0%
#453154
0$
#455000
b10110 6
b110010100000000000000000000000 :
1!
1%
#460000
0%
#460967
1$
#465000
b10111 6
b1100101000000000000000000000000 :
1!
1%
#468780
0$
#470000
0%
#475000
b11000 6
b11001010000000000000000000000000 :
1!
1%
#476593
1$
#480000
0%
#484406
0$
#485000
b11001 6
b110010100000000000000000000000000 :
1!
1%
#490000
0%
#492219
1$
#495000
b11010 6
b1100101000000000000000000000000000 :
1!
1%
#500000
0%
#500032
0$
#505000
b11011 6
b11001010000000000000000000000000000 :
1!
1%
#507845
1$
#510000
0%
#515000
b11100 6
b110010100000000000000000000000000000 :
1!
1%
#515658
0$
#520000
0%
#523471
1$
#525000
b11101 6
b1100101000000000000000000000000000000 :
1!
1%
#530000
0%
#531284
0$
#535000
b11110 6
b11001010000000000000000000000000000000 :
1!
1%
#539097
1$
#540000
0%
#545000
b11111 6
b110010100000000000000000000000000000000 :
1!
1%
#546910
0$
#550000
0%
#554723
1$
#555000
b100000 6
b1100101000000000000000000000000000000000 :
1!
1%
#560000
0%
#562536
0$
#565000
b100001 6
b11001010000000000000000000000000000000000 :
1!
1%
#570000
0%
#570349
1$
#575000
b100010 6
b110010100000000000000000000000000000000000 :
1!
1%
#578162
0$
#580000
0%
#585000
b100011 6
b1100101000000000000000000000000000000000000 :
1!
1%
#585975
1$
#590000
0%
#593788
0$
#595000
b100100 6
b11001010000000000000000000000000000000000000 :
1!
1%
#600000
0%
#601601
1$
#605000
b100101 6
b110010100000000000000000000000000000000000000 :
1!
1%
#609414
0$
#610000
0%
#615000
b100110 6
b1100101000000000000000000000000000000000000000 :
1!
1%
#617227
1$
#620000
0%
#625000
b100111 6
b11001010000000000000000000000000000000000000000 :
1!
1%
#625040
0$
#630000
0%
#632853
1$
#635000
b101000 6
b110010100000000000000000000000000000000000000000 :
1!
1%
#640000
0%
#640666
0$
#645000
b101001 6
b1100101000000000000000000000000000000000000000000 :
1!
1%
#648479
1$
#650000
0%
#655000
b101010 6
b11001010000000000000000000000000000000000000000000 :
1!
1%
#656292
0$
#660000
0%
#664105
1$
#665000
b101011 6
b110010100000000000000000000000000000000000000000000 :
1!
1%
#670000
0%
#671918
0$
#675000
b101100 6
b1100101000000000000000000000000000000000000000000000 :
1!
1%
#679731
1$
#680000
0%
#685000
b101101 6
b11001010000000000000000000000000000000000000000000000 :
1!
1%
#687544
0$
#690000
0%
#695000
b101110 6
b110010100000000000000000000000000000000000000000000000 :
1!
1%
#695357
1$
#700000
0%
#703170
0$
#705000
b101111 6
b1100101000000000000000000000000000000000000000000000000 :
1!
1%
#710000
0%
#710983
1$
#715000
b110000 6
b11001010000000000000000000000000000000000000000000000000 :
1!
1%
#718796
0$
#720000
0%
#725000
b110001 6
b10010100000000000000000000000000000000000000000000000000 :
1"
1!
1%
#726609
1$
#730000
0%
#734422
0$
#735000
b110010 6
b101000000000000000000000000000000000000000000000000000 :
1!
1%
#740000
0%
#742235
1$
#745000
b110011 6
b1010000000000000000000000000000000000000000000000000000 :
0"
1!
1%
#750000
0%
#750048
0$
#755000
b110100 6
b10100000000000000000000000000000000000000000000000000000 :
1!
1%
#757861
1$
#760000
0%
#765000
b110101 6
b1000000000000000000000000000000000000000000000000000000 :
1"
1!
1%
#765674
0$
#770000
0%
#773487
1$
#775000
b110110 6
b10000000000000000000000000000000000000000000000000000000 :
0"
1!
1%
#780000
0%
#781300
0$
#785000
b110111 6
b0 :
1"
1!
1%
#789113
1$
#790000
0%
#795000
b0 ;
09
b111000 6
0"
1!
1%
#796926
0$
#800000
0%
#804739
1$
#805000
0!
1%
