manchester_encoder_100m.v
// ============================================================================
// Manchester Encoder - 100MHz Single-Clock with DDR Output
// ============================================================================
// Encoding scheme: 4 clock cycles per bit
//   - Bit rate: 25 Mbps (data) → 50 Mbps Manchester line rate
//   - Clock period: 10ns @ 100MHz
//   - Bit period: 40ns (4 clock cycles)
//   - Encoding: bit=0 -> 0→1 transition, bit=1 -> 1→0 transition
//
// Interface:
//   - Input:  bit_in, bit_valid (ready-valid handshake)
//   - Output: bit_ready, ddr_p, ddr_n (differential DDR)
// ============================================================================

module manchester_encoder_100m (
    input  wire clk_sys,      // 100MHz system clock
    input  wire rst_n,
    input  wire tx_en,        // Transmit enable (active high)

    // Serial bit input (ready-valid handshake)
    input  wire bit_in,       // Data bit to encode
    input  wire bit_valid,    // Input valid
    output wire bit_ready,    // Ready to accept new bit

    // Differential DDR output
    output wire ddr_p,        // Positive phase
    output wire ddr_n         // Negative phase (complement)
);

    // ========================================================================
    // Half-cycle counter (4 cycles per bit)
    // ========================================================================
    reg [1:0] half_cnt;

    always @(posedge clk_sys or negedge rst_n) begin
        if (!rst_n) begin
            half_cnt <= 2'b00;
        end else if (tx_en && bit_valid && bit_ready) begin
            // New bit accepted, start counting from 0
            half_cnt <= 2'b01;
        end else if (tx_en && (half_cnt != 2'b11)) begin
            // Continue counting
            half_cnt <= half_cnt + 1'b1;
        end else if (tx_en && (half_cnt == 2'b11)) begin
            // End of bit, reset to 0
            half_cnt <= 2'b00;
        end else begin
            // Disabled
            half_cnt <= 2'b00;
        end
    end

    // ========================================================================
    // Output generation - 2:1 MUX per half cycle
    // ========================================================================
    // First half (cycles 0-1): output original bit
    // Second half (cycles 2-3): output inverted bit
    wire first_half = (half_cnt < 2'b10);

    assign ddr_p = tx_en ? (first_half ? bit_in : ~bit_in) : 1'b0;
    assign ddr_n = ~ddr_p;  // Complementary output

    // ========================================================================
    // Ready signal - asserted at end of bit (cycle 3)
    // ========================================================================
    assign bit_ready = (half_cnt == 2'b11);

endmodule

testbench/tb_manchester_encoder.v
`timescale 1ns / 1ps

module tb_manchester_encoder;

    reg clk_sys;
    reg rst_n;
    reg tx_en;
    reg bit_in;
    reg bit_valid;
    wire bit_ready;
    wire ddr_p;
    wire ddr_n;

    // Clock generation (100MHz)
    initial begin
        clk_sys = 0;
        forever #5 clk_sys = ~clk_sys;
    end

    // DUT
    manchester_encoder_100m u_dut (
        .clk_sys(clk_sys),
        .rst_n(rst_n),
        .tx_en(tx_en),
        .bit_in(bit_in),
        .bit_valid(bit_valid),
        .bit_ready(bit_ready),
        .ddr_p(ddr_p),
        .ddr_n(ddr_n)
    );

    initial begin
        $dumpfile("tb_manchester_encoder.vcd");
        $dumpvars(0, tb_manchester_encoder);

        // Initialize
        rst_n = 0;
        tx_en = 0;
        bit_in = 0;
        bit_valid = 0;

        #100;
        rst_n = 1;
        #20;
        tx_en = 1;

        // Send bit 0
        wait(bit_ready);
        @(posedge clk_sys);
        bit_in = 0;
        bit_valid = 1;
        @(posedge clk_sys);
        bit_valid = 0;

        // Send bit 1
        wait(bit_ready);
        @(posedge clk_sys);
        bit_in = 1;
        bit_valid = 1;
        @(posedge clk_sys);
        bit_valid = 0;
        
        // Send bit 0 again
        wait(bit_ready);
        @(posedge clk_sys);
        bit_in = 0;
        bit_valid = 1;
        @(posedge clk_sys);
        bit_valid = 0;

        #200;
        $finish;
    end

endmodule

testbench/tb_manchester_encoder.vcd
$date
	Thu Nov 20 16:26:29 2025
$end
$version
	Icarus Verilog
$end
$timescale
	1ps
$end
$scope module tb_manchester_encoder $end
$var wire 1 ! ddr_p $end
$var wire 1 " ddr_n $end
$var wire 1 # bit_ready $end
$var reg 1 $ bit_in $end
$var reg 1 % bit_valid $end
$var reg 1 & clk_sys $end
$var reg 1 ' rst_n $end
$var reg 1 ( tx_en $end
$scope module u_dut $end
$var wire 1 $ bit_in $end
$var wire 1 % bit_valid $end
$var wire 1 & clk_sys $end
$var wire 1 " ddr_n $end
$var wire 1 ' rst_n $end
$var wire 1 ( tx_en $end
$var wire 1 ) first_half $end
$var wire 1 ! ddr_p $end
$var wire 1 # bit_ready $end
$var reg 2 * half_cnt [1:0] $end
$upscope $end
$upscope $end
$enddefinitions $end
$comment Show the parameter values. $end
$dumpall
$end
#0
$dumpvars
b0 *
1)
0(
0'
0&
0%
0$
0#
1"
0!
$end
#5000
1&
#10000
0&
#15000
1&
#20000
0&
#25000
1&
#30000
0&
#35000
1&
#40000
0&
#45000
1&
#50000
0&
#55000
1&
#60000
0&
#65000
1&
#70000
0&
#75000
1&
#80000
0&
#85000
1&
#90000
0&
#95000
1&
#100000
0&
1'
#105000
1&
#110000
0&
#115000
1&
#120000
0&
1(
#125000
b1 *
1&
#130000
0&
#135000
0"
1!
0)
b10 *
1&
#140000
0&
#145000
1#
b11 *
1&
#150000
0&
#155000
1"
0!
1)
0#
b1 *
1%
1&
#160000
0&
#165000
0"
1!
0)
b10 *
0%
1&
#170000
0&
#175000
1#
b11 *
1&
#180000
0&
#185000
1)
0#
b1 *
0"
1!
1%
1$
1&
#190000
0&
#195000
1"
0!
0)
b10 *
0%
1&
#200000
0&
#205000
1#
b11 *
1&
#210000
0&
#215000
1)
0#
b1 *
1"
0!
1%
0$
1&
#220000
0&
#225000
0"
1!
0)
b10 *
0%
1&
#230000
0&
#235000
1#
b11 *
1&
#240000
0&
#245000
1"
0!
1)
0#
b0 *
1&
#250000
0&
#255000
b1 *
1&
#260000
0&
#265000
0"
1!
0)
b10 *
1&
#270000
0&
#275000
1#
b11 *
1&
#280000
0&
#285000
1"
0!
1)
0#
b0 *
1&
#290000
0&
#295000
b1 *
1&
#300000
0&
#305000
0"
1!
0)
b10 *
1&
#310000
0&
#315000
1#
b11 *
1&
#320000
0&
#325000
1"
0!
1)
0#
b0 *
1&
#330000
0&
#335000
b1 *
1&
#340000
0&
#345000
0"
1!
0)
b10 *
1&
#350000
0&
#355000
1#
b11 *
1&
#360000
0&
#365000
1"
0!
1)
0#
b0 *
1&
#370000
0&
#375000
b1 *
1&
#380000
0&
#385000
0"
1!
0)
b10 *
1&
#390000
0&
#395000
1#
b11 *
1&
#400000
0&
#405000
1"
0!
1)
0#
b0 *
1&
#410000
0&
#415000
b1 *
1&
#420000
0&
#425000
0"
1!
0)
b10 *
1&
