spi_master_rhs2116.v
// ============================================================================
// SPI Master for RHS2116 - 64MHz Input, 16MHz SCLK
// ============================================================================
// Clock: 64MHz dedicated PLL output (clk_spi)
// SCLK: 16MHz (64MHz / 4)
// Data rate: 32-bit frames @ 16MHz = 446.4k frames/sec (16 channels)
//
// Features:
//   - Automatic channel polling (0-15) with CONVERT commands
//   - First 2 frames discarded (RHS2116 latency compensation)
//   - Mode 1: CPOL=0, CPHA=1 (sample on falling edge)
//
// Interface:
//   - Control: enable (clk_sys domain), synced to clk_spi
//   - SPI: cs_n, sclk, mosi, miso
//   - Output: data_out[31:0], data_valid (clk_sys domain, synced)
// ============================================================================

module spi_master_rhs2116 (
    input  wire        clk_spi,    // 64MHz (dedicated PLL output)
    input  wire        rst_n,
    input  wire        enable,     // From clk_sys domain (will be synced)

    // SPI interface
    output reg         cs_n,
    output wire        sclk,       // 16MHz = 64MHz / 4
    output reg         mosi,
    input  wire        miso,

    // Output data (clk_spi domain)
    output reg [31:0]  data_out,
    output reg         data_valid
);

    // ========================================================================
    // Parameters
    // ========================================================================
    localparam CMD_CONVERT     = 2'b00;
    localparam CMD_PADDING     = 16'h0000;
    localparam GAP_CYCLES      = 6'h0F;  // 16 cycles
    localparam DISCARD_FRAMES  = 8'd2;
    localparam SCLK_DIV_MAX    = 2'b11;  // Divide by 4
    localparam SCLK_RISING_EDGE = 2'b01;
    localparam SCLK_FALLING_EDGE = 2'b11;

    // ========================================================================
    // Input synchronization (enable from clk_sys -> clk_spi)
    // ========================================================================
    reg enable_spi1, enable_spi2;

    always @(posedge clk_spi) begin
        enable_spi1 <= enable;
        enable_spi2 <= enable_spi1;
    end

    wire enable_sync = enable_spi2;  // Synchronized enable signal

    // ========================================================================
    // SCLK generation: 64MHz / 4 = 16MHz
    // ========================================================================
    reg [1:0] sclk_cnt;

    always @(posedge clk_spi or negedge rst_n) begin
        if (!rst_n)
            sclk_cnt <= 2'b00;
        else
            sclk_cnt <= sclk_cnt + 1'b1;
    end

    assign sclk = sclk_cnt[1];  // 16MHz output (toggle every 4 cycles)

    // SCLK edge detection
    wire sclk_falling = (sclk_cnt == SCLK_FALLING_EDGE);  // Falling edge (sample MISO)
    wire sclk_rising  = (sclk_cnt == SCLK_RISING_EDGE);  // Rising edge (update MOSI)

    // ========================================================================
    // RHS2116 CONVERT command generation
    // ========================================================================
    wire [31:0] convert_cmd = {
        CMD_CONVERT,    // CONVERT command
        1'b0,     // U
        1'b0,     // M
        1'b1,     // D (DC-coupled, 10-bit mode)
        1'b0,     // H
        4'b0000,
        curr_chan,  // Channel number (6-bit)
        CMD_PADDING
    };

    // ========================================================================
    // State machine
    // ========================================================================
    localparam IDLE  = 3'b000;
    localparam LOAD  = 3'b001;
    localparam XFER  = 3'b010;
    localparam GAP   = 3'b011;
    localparam DONE  = 3'b100;

    reg [2:0] state;
    reg [5:0] bit_cnt;      // 0-31
    reg [5:0] gap_cnt;      // CS gap counter (16 cycles)
    reg [3:0] curr_chan;    // Current channel (0-15)
    reg [7:0] frame_cnt;    // Frame counter (discard first 2)

    reg [31:0] shifter_tx;  // Transmit shift register
    reg [31:0] shifter_rx;  // Receive shift register

    // Output data (clk_spi domain)
    // Note: Downstream modules must handle CDC (e.g., via Async FIFO)
    reg [31:0] data_out_reg;
    reg        data_valid_reg;

    // ========================================================================
    // Main state machine
    // ========================================================================
    always @(posedge clk_spi or negedge rst_n) begin
        if (!rst_n) begin
            state         <= IDLE;
            cs_n          <= 1'b1;
            mosi          <= 1'b0;
            bit_cnt       <= 6'b0;
            gap_cnt       <= 6'b0;
            curr_chan     <= 4'b0;
            frame_cnt     <= 8'b0;
            shifter_tx    <= 32'b0;
            shifter_rx    <= 32'b0;
            data_out_reg   <= 32'b0;
            data_valid_reg <= 1'b0;
            data_out       <= 32'b0;
            data_valid     <= 1'b0;
        end else begin
            data_valid_reg <= 1'b0;  // Default

            case (state)
                // IDLE: Wait for enable
                IDLE: begin
                    cs_n <= 1'b1;
                    mosi <= 1'b0;

                    if (enable_sync) begin
                        state <= LOAD;
                    end
                end

                // LOAD: Setup new CONVERT command
                LOAD: begin
                    cs_n       <= 1'b0;           // Assert CS
                    shifter_tx <= convert_cmd;
                    mosi       <= convert_cmd[31]; // First bit
                    bit_cnt    <= 6'b0;
                    state      <= XFER;
                end

                // XFER: Transfer 32 bits
                XFER: begin
                    cs_n <= 1'b0;

                    // On falling edge: sample MISO
                    if (sclk_falling) begin
                        shifter_rx <= {shifter_rx[30:0], miso};

                        if (bit_cnt == 6'd31) begin
                            // Transfer complete
                            data_out_reg <= {shifter_rx[30:0], miso};
                            frame_cnt <= frame_cnt + 1'b1;

                            // Discard first 2 frames (RHS2116 latency)
                            if (frame_cnt >= DISCARD_FRAMES) begin
                                data_valid_reg <= 1'b1;
                                $display("SPI Master: Received frame %d, data %h", frame_cnt, {shifter_rx[30:0], miso});
                            end

                            state <= GAP;
                        end else begin
                            bit_cnt <= bit_cnt + 1'b1;
                        end
                    end

                    // On rising edge: update MOSI
                    if (sclk_rising && (bit_cnt < 6'd31)) begin
                        mosi <= shifter_tx[31];
                        shifter_tx <= {shifter_tx[30:0], 1'b0};
                    end
                end

                // GAP: CS high time between frames
                GAP: begin
                    cs_n <= 1'b1;
                    mosi <= 1'b0;

                    if (gap_cnt >= GAP_CYCLES) begin  // 16 cycles gap
                        gap_cnt <= 6'b0;
                        curr_chan <= curr_chan + 1'b1;  // Next channel
                        state <= enable_sync ? LOAD : IDLE;
                    end else begin
                        gap_cnt <= gap_cnt + 1'b1;
                    end
                end

                default: begin
                    state <= IDLE;
                end
            endcase

            // Output assignment
            data_out   <= data_out_reg;
            data_valid <= data_valid_reg;
        end
    end

endmodule

testbench/tb_spi_master.v
`timescale 1ns / 1ps

module tb_spi_master;

    reg clk_spi;
    reg rst_n;
    reg enable;
    reg miso;
    wire cs_n;
    wire sclk;
    wire mosi;
    wire [31:0] data_out;
    wire data_valid;

    // Clock generation (64MHz)
    initial begin
        clk_spi = 0;
        forever #7.8125 clk_spi = ~clk_spi;
    end

    // DUT
    spi_master_rhs2116 u_dut (
        .clk_spi(clk_spi),
        .rst_n(rst_n),
        .enable(enable),
        .cs_n(cs_n),
        .sclk(sclk),
        .mosi(mosi),
        .miso(miso),
        .data_out(data_out),
        .data_valid(data_valid)
    );

    // Simulated Slave
    reg [31:0] slave_data = 32'hDEADBEEF;
    reg [5:0] bit_cnt;
    
    always @(negedge cs_n) begin
        bit_cnt <= 0;
    end

    always @(posedge sclk) begin
        if (!cs_n) begin
            miso <= slave_data[31 - bit_cnt];
            bit_cnt <= bit_cnt + 1;
        end
    end

    initial begin
        $dumpfile("tb_spi_master.vcd");
        $dumpvars(0, tb_spi_master);

        rst_n = 0;
        enable = 0;
        miso = 0;

        #100;
        rst_n = 1;
        #100;
        enable = 1;

        // Wait for a few frames
        repeat(3) @(posedge data_valid);
        
        $display("Received data: %h", data_out);
        if (data_out == 32'hDEADBEEF)
            $display("SPI Test PASSED");
        else
            $display("SPI Test FAILED");

        #1000;
        $finish;
    end

endmodule

testbench/tb_spi_master.vcd
$date
	Thu Nov 20 16:26:50 2025
$end
$version
	Icarus Verilog
$end
$timescale
	1ps
$end
$scope module tb_spi_master $end
$var wire 1 ! sclk $end
$var wire 1 " mosi $end
$var wire 1 # data_valid $end
$var wire 32 $ data_out [31:0] $end
$var wire 1 % cs_n $end
$var reg 6 & bit_cnt [5:0] $end
$var reg 1 ' clk_spi $end
$var reg 1 ( enable $end
$var reg 1 ) miso $end
$var reg 1 * rst_n $end
$var reg 32 + slave_data [31:0] $end
$scope module u_dut $end
$var wire 1 ' clk_spi $end
$var wire 1 ( enable $end
$var wire 1 , enable_sync $end
$var wire 1 ) miso $end
$var wire 1 * rst_n $end
$var wire 1 - sclk_rising $end
$var wire 1 . sclk_falling $end
$var wire 1 ! sclk $end
$var wire 32 / convert_cmd [31:0] $end
$var parameter 2 0 CMD_CONVERT $end
$var parameter 16 1 CMD_PADDING $end
$var parameter 8 2 DISCARD_FRAMES $end
$var parameter 3 3 DONE $end
$var parameter 3 4 GAP $end
$var parameter 6 5 GAP_CYCLES $end
$var parameter 3 6 IDLE $end
$var parameter 3 7 LOAD $end
$var parameter 2 8 SCLK_DIV_MAX $end
$var parameter 2 9 SCLK_FALLING_EDGE $end
$var parameter 2 : SCLK_RISING_EDGE $end
$var parameter 3 ; XFER $end
$var reg 6 < bit_cnt [5:0] $end
$var reg 1 % cs_n $end
$var reg 4 = curr_chan [3:0] $end
$var reg 32 > data_out [31:0] $end
$var reg 32 ? data_out_reg [31:0] $end
$var reg 1 # data_valid $end
$var reg 1 @ data_valid_reg $end
$var reg 1 A enable_spi1 $end
$var reg 1 B enable_spi2 $end
$var reg 8 C frame_cnt [7:0] $end
$var reg 6 D gap_cnt [5:0] $end
$var reg 1 " mosi $end
$var reg 2 E sclk_cnt [1:0] $end
$var reg 32 F shifter_rx [31:0] $end
$var reg 32 G shifter_tx [31:0] $end
$var reg 3 H state [2:0] $end
$upscope $end
$upscope $end
$enddefinitions $end
$comment Show the parameter values. $end
$dumpall
b10 ;
b1 :
b11 9
b11 8
b1 7
b0 6
b1111 5
b11 4
b100 3
b10 2
b0 1
b0 0
$end
#0
$dumpvars
b0 H
b0 G
b0 F
b0 E
b0 D
b0 C
xB
xA
0@
b0 ?
b0 >
b0 =
b0 <
b10000000000000000000000000 /
0.
0-
x,
b11011110101011011011111011101111 +
0*
0)
0(
0'
bx &
1%
b0 $
0#
0"
0!
$end
#7813
0A
1'
#15626
0'
#23439
0,
0B
1'
#31252
0'
#39065
1'
#46878
0'
#54691
1'
#62504
0'
#70317
1'
#78130
0'
#85943
1'
#93756
0'
#100000
1*
#101569
1-
b1 E
1'
#109382
0'
#117195
1!
0-
b10 E
1'
#125008
0'
#132821
1.
b11 E
1'
#140634
0'
#148447
0!
0.
b0 E
1'
#156260
0'
#164073
1-
b1 E
1'
#171886
0'
#179699
1!
0-
b10 E
1'
#187512
0'
#195325
1.
b11 E
1'
#200000
1(
#203138
0'
#210951
0!
0.
b0 E
1A
1'
#218764
0'
#226577
1-
b1 E
1,
1B
1'
#234390
0'
#242203
1!
0-
b10 E
b1 H
1'
#250016
0'
#257829
b0 &
b10 H
b10000000000000000000000000 G
0%
1.
b11 E
1'
#265642
0'
#273455
0!
0.
b0 E
b1 <
1'
#281268
0'
#289081
1-
b1 E
1'
#296894
0'
#304707
b1 &
1)
1!
0-
b10 E
b100000000000000000000000000 G
1'
#312520
0'
#320333
1.
b11 E
1'
#328146
0'
#335959
0!
0.
b0 E
b10 <
b1 F
1'
#343772
0'
#351585
1-
b1 E
1'
#359398
0'
#367211
b10 &
1!
0-
b10 E
b1000000000000000000000000000 G
1'
#375024
0'
#382837
1.
b11 E
1'
#390650
0'
#398463
0!
0.
b0 E
b11 <
b11 F
1'
#406276
0'
#414089
1-
b1 E
1'
#421902
0'
#429715
b11 &
0)
1!
0-
b10 E
b10000000000000000000000000000 G
1'
#437528
0'
#445341
1.
b11 E
1'
#453154
0'
#460967
0!
0.
b0 E
b100 <
b110 F
1'
#468780
0'
#476593
1-
b1 E
1'
#484406
0'
#492219
b100 &
1)
1!
0-
b10 E
b100000000000000000000000000000 G
1'
#500032
0'
#507845
1.
b11 E
1'
#515658
0'
#523471
0!
0.
b0 E
b101 <
b1101 F
1'
#531284
0'
#539097
1-
b1 E
1'
#546910
0'
#554723
b101 &
1!
0-
b10 E
b1000000000000000000000000000000 G
1'
#562536
0'
#570349
1.
b11 E
1'
#578162
0'
#585975
0!
0.
b0 E
b110 <
b11011 F
1'
#593788
0'
#601601
1-
b1 E
1'
#609414
0'
#617227
b110 &
1!
0-
b10 E
b10000000000000000000000000000000 G
1'
#625040
0'
#632853
1.
b11 E
1'
#640666
0'
#648479
0!
0.
b0 E
b111 <
b110111 F
1'
#656292
0'
#664105
1-
b1 E
1'
#671918
0'
#679731
b111 &
1!
0-
b10 E
b0 G
1"
1'
#687544
0'
#695357
1.
b11 E
1'
#703170
0'
#710983
0!
0.
b0 E
b1000 <
b1101111 F
1'
#718796
0'
#726609
1-
b1 E
1'
#734422
0'
#742235
b1000 &
0)
1!
0-
b10 E
0"
1'
#750048
0'
#757861
1.
b11 E
1'
#765674
0'
#773487
0!
0.
b0 E
b1001 <
b11011110 F
1'
#781300
0'
#789113
1-
b1 E
1'
#796926
0'
#804739
b1001 &
1)
1!
0-
b10 E
1'
#812552
0'
#820365
1.
b11 E
1'
#828178
0'
#835991
0!
0.
b0 E
b1010 <
b110111101 F
1'
#843804
0'
#851617
1-
b1 E
1'
#859430
0'
#867243
b1010 &
0)
1!
0-
b10 E
1'
#875056
0'
#882869
1.
b11 E
1'
#890682
0'
#898495
0!
0.
b0 E
b1011 <
b1101111010 F
1'
#906308
0'
#914121
1-
b1 E
1'
#921934
0'
#929747
b1011 &
1)
1!
0-
b10 E
1'
#937560
0'
#945373
1.
b11 E
1'
#953186
0'
#960999
0!
0.
b0 E
b1100 <
b11011110101 F
1'
#968812
0'
#976625
1-
b1 E
1'
#984438
0'
#992251
b1100 &
0)
1!
0-
b10 E
1'
#1000064
0'
#1007877
1.
b11 E
1'
#1015690
0'
#1023503
0!
0.
b0 E
b1101 <
b110111101010 F
1'
#1031316
0'
#1039129
1-
b1 E
1'
#1046942
0'
#1054755
b1101 &
1)
1!
0-
b10 E
1'
#1062568
0'
#1070381
1.
b11 E
1'
#1078194
0'
#1086007
0!
0.
b0 E
b1110 <
b1101111010101 F
1'
#1093820
0'
#1101633
1-
b1 E
1'
#1109446
0'
#1117259
b1110 &
1!
0-
b10 E
1'
#1125072
0'
#1132885
1.
b11 E
1'
#1140698
0'
#1148511
0!
0.
b0 E
b1111 <
b11011110101011 F
1'
#1156324
0'
#1164137
1-
b1 E
1'
#1171950
0'
#1179763
b1111 &
0)
1!
0-
b10 E
1'
#1187576
0'
#1195389
1.
b11 E
1'
#1203202
0'
#1211015
0!
0.
b0 E
b10000 <
b110111101010110 F
1'
#1218828
0'
#1226641
1-
b1 E
1'
#1234454
0'
#1242267
b10000 &
1)
1!
0-
b10 E
1'
#1250080
0'
#1257893
1.
b11 E
1'
#1265706
0'
#1273519
0!
0.
b0 E
b10001 <
b1101111010101101 F
1'
#1281332
0'
#1289145
1-
b1 E
1'
#1296958
0'
#1304771
b10001 &
1!
0-
b10 E
1'
#1312584
0'
#1320397
1.
b11 E
1'
#1328210
0'
#1336023
0!
0.
b0 E
b10010 <
b11011110101011011 F
1'
#1343836
0'
#1351649
1-
b1 E
1'
#1359462
0'
#1367275
b10010 &
0)
1!
0-
b10 E
1'
#1375088
0'
#1382901
1.
b11 E
1'
#1390714
0'
#1398527
0!
0.
b0 E
b10011 <
b110111101010110110 F
1'
#1406340
0'
#1414153
1-
b1 E
1'
#1421966
0'
#1429779
b10011 &
1)
1!
0-
b10 E
1'
#1437592
0'
#1445405
1.
b11 E
1'
#1453218
0'
#1461031
0!
0.
b0 E
b10100 <
b1101111010101101101 F
1'
#1468844
0'
#1476657
1-
b1 E
1'
#1484470
0'
#1492283
b10100 &
1!
0-
b10 E
1'
#1500096
0'
#1507909
1.
b11 E
1'
#1515722
0'
#1523535
0!
0.
b0 E
b10101 <
b11011110101011011011 F
1'
#1531348
0'
#1539161
1-
b1 E
1'
#1546974
0'
#1554787
b10101 &
1!
0-
b10 E
1'
#1562600
0'
#1570413
1.
b11 E
1'
#1578226
0'
#1586039
0!
0.
b0 E
b10110 <
b110111101010110110111 F
1'
#1593852
0'
#1601665
1-
b1 E
1'
#1609478
0'
#1617291
b10110 &
1!
0-
b10 E
1'
#1625104
0'
#1632917
1.
b11 E
1'
#1640730
0'
#1648543
0!
0.
b0 E
b10111 <
b1101111010101101101111 F
1'
#1656356
0'
#1664169
1-
b1 E
1'
#1671982
0'
#1679795
b10111 &
1!
0-
b10 E
1'
#1687608
0'
#1695421
1.
b11 E
1'
#1703234
0'
#1711047
0!
0.
b0 E
b11000 <
b11011110101011011011111 F
1'
#1718860
0'
#1726673
1-
b1 E
1'
#1734486
0'
#1742299
b11000 &
0)
1!
0-
b10 E
1'
#1750112
0'
#1757925
1.
b11 E
1'
#1765738
0'
#1773551
0!
0.
b0 E
b11001 <
b110111101010110110111110 F
1'
#1781364
0'
#1789177
1-
b1 E
1'
#1796990
0'
#1804803
b11001 &
1)
1!
0-
b10 E
1'
#1812616
0'
#1820429
1.
b11 E
1'
#1828242
0'
#1836055
0!
0.
b0 E
b11010 <
b1101111010101101101111101 F
1'
#1843868
0'
#1851681
1-
b1 E
1'
#1859494
0'
#1867307
b11010 &
1!
0-
b10 E
1'
#1875120
0'
#1882933
1.
b11 E
1'
#1890746
0'
#1898559
0!
0.
b0 E
b11011 <
b11011110101011011011111011 F
1'
#1906372
0'
#1914185
1-
b1 E
1'
#1921998
0'
#1929811
b11011 &
1!
0-
b10 E
1'
#1937624
0'
#1945437
1.
b11 E
1'
#1953250
0'
#1961063
0!
0.
b0 E
b11100 <
b110111101010110110111110111 F
1'
#1968876
0'
#1976689
1-
b1 E
1'
#1984502
0'
#1992315
b11100 &
0)
1!
0-
b10 E
1'
#2000128
0'
#2007941
1.
b11 E
1'
#2015754
0'
#2023567
0!
0.
b0 E
b11101 <
b1101111010101101101111101110 F
1'
#2031380
0'
#2039193
1-
b1 E
1'
#2047006
0'
#2054819
b11101 &
1)
1!
0-
b10 E
1'
#2062632
0'
#2070445
1.
b11 E
1'
#2078258
0'
#2086071
0!
0.
b0 E
b11110 <
b11011110101011011011111011101 F
1'
#2093884
0'
#2101697
1-
b1 E
1'
#2109510
0'
#2117323
b11110 &
1!
0-
b10 E
1'
#2125136
0'
#2132949
1.
b11 E
1'
#2140762
0'
#2148575
0!
0.
b0 E
b11111 <
b110111101010110110111110111011 F
1'
#2156388
0'
#2164201
1-
b1 E
1'
#2172014
0'
#2179827
b11111 &
1!
0-
b10 E
1'
#2187640
0'
#2195453
1.
b11 E
1'
#2203266
0'
#2211079
0!
0.
b0 E
b11 H
b1 C
b1101111010101101101111101110111 ?
b1101111010101101101111101110111 F
1'
#2218892
0'
#2226705
b1101111010101101101111101110111 $
b1101111010101101101111101110111 >
b1 D
1%
1-
b1 E
1'
#2234518
0'
#2242331
1!
0-
b10 E
b10 D
1'
#2250144
0'
#2257957
b11 D
1.
b11 E
1'
#2265770
0'
#2273583
0!
0.
b0 E
b100 D
1'
#2281396
0'
#2289209
b101 D
1-
b1 E
1'
#2297022
0'
#2304835
1!
0-
b10 E
b110 D
1'
#2312648
0'
#2320461
b111 D
1.
b11 E
1'
#2328274
0'
#2336087
0!
0.
b0 E
b1000 D
1'
#2343900
0'
#2351713
b1001 D
1-
b1 E
1'
#2359526
0'
#2367339
1!
0-
b10 E
b1010 D
1'
#2375152
0'
#2382965
b1011 D
1.
b11 E
1'
#2390778
0'
#2398591
0!
0.
b0 E
b1100 D
1'
#2406404
0'
#2414217
b1101 D
1-
b1 E
1'
#2422030
0'
#2429843
1!
0-
b10 E
b1110 D
1'
#2437656
0'
#2445469
b1111 D
1.
b11 E
1'
#2453282
0'
#2461095
0!
0.
b0 E
b1 H
b10000000010000000000000000 /
b1 =
b0 D
1'
#2468908
0'
#2476721
b0 &
b10 H
b0 <
b10000000010000000000000000 G
0%
1-
b1 E
1'
#2484534
0'
#2492347
b1 &
1!
0-
b10 E
b100000000100000000000000000 G
1'
#2500160
0'
#2507973
1.
b11 E
1'
#2515786
0'
#2523599
0!
0.
b0 E
b1 <
b11011110101011011011111011101111 F
1'
#2531412
0'
#2539225
1-
b1 E
1'
#2547038
0'
#2554851
b10 &
1!
0-
b10 E
b1000000001000000000000000000 G
1'
#2562664
0'
#2570477
1.
b11 E
1'
#2578290
0'
#2586103
0!
0.
b0 E
b10 <
b10111101010110110111110111011111 F
1'
#2593916
0'
#2601729
1-
b1 E
1'
#2609542
0'
#2617355
b11 &
0)
1!
0-
b10 E
b10000000010000000000000000000 G
1'
#2625168
0'
#2632981
1.
b11 E
1'
#2640794
0'
#2648607
0!
0.
b0 E
b11 <
b1111010101101101111101110111110 F
1'
#2656420
0'
#2664233
1-
b1 E
1'
#2672046
0'
#2679859
b100 &
1)
1!
0-
b10 E
b100000000100000000000000000000 G
1'
#2687672
0'
#2695485
1.
b11 E
1'
#2703298
0'
#2711111
0!
0.
b0 E
b100 <
b11110101011011011111011101111101 F
1'
#2718924
0'
#2726737
1-
b1 E
1'
#2734550
0'
#2742363
b101 &
1!
0-
b10 E
b1000000001000000000000000000000 G
1'
#2750176
0'
#2757989
1.
b11 E
1'
#2765802
0'
#2773615
0!
0.
b0 E
b101 <
b11101010110110111110111011111011 F
1'
#2781428
0'
#2789241
1-
b1 E
1'
#2797054
0'
#2804867
b110 &
1!
0-
b10 E
b10000000010000000000000000000000 G
1'
#2812680
0'
#2820493
1.
b11 E
1'
#2828306
0'
#2836119
0!
0.
b0 E
b110 <
b11010101101101111101110111110111 F
1'
#2843932
0'
#2851745
1-
b1 E
1'
#2859558
0'
#2867371
b111 &
1!
0-
b10 E
b100000000000000000000000 G
1"
1'
#2875184
0'
#2882997
1.
b11 E
1'
#2890810
0'
#2898623
0!
0.
b0 E
b111 <
b10101011011011111011101111101111 F
1'
#2906436
0'
#2914249
1-
b1 E
1'
#2922062
0'
#2929875
b1000 &
0)
1!
0-
b10 E
b1000000000000000000000000 G
0"
1'
#2937688
0'
#2945501
1.
b11 E
1'
#2953314
0'
#2961127
0!
0.
b0 E
b1000 <
b1010110110111110111011111011110 F
1'
#2968940
0'
#2976753
1-
b1 E
1'
#2984566
0'
#2992379
b1001 &
1)
1!
0-
b10 E
b10000000000000000000000000 G
1'
#3000192
0'
#3008005
1.
b11 E
1'
#3015818
0'
#3023631
0!
0.
b0 E
b1001 <
b10101101101111101110111110111101 F
1'
#3031444
0'
#3039257
1-
b1 E
1'
#3047070
0'
#3054883
b1010 &
0)
1!
0-
b10 E
b100000000000000000000000000 G
1'
#3062696
0'
#3070509
1.
b11 E
1'
#3078322
0'
#3086135
0!
0.
b0 E
b1010 <
b1011011011111011101111101111010 F
1'
#3093948
0'
#3101761
1-
b1 E
1'
#3109574
0'
#3117387
b1011 &
1)
1!
0-
b10 E
b1000000000000000000000000000 G
1'
#3125200
0'
#3133013
1.
b11 E
1'
#3140826
0'
#3148639
0!
0.
b0 E
b1011 <
b10110110111110111011111011110101 F
1'
#3156452
0'
#3164265
1-
b1 E
1'
#3172078
0'
#3179891
b1100 &
0)
1!
0-
b10 E
b10000000000000000000000000000 G
1'
#3187704
0'
#3195517
1.
b11 E
1'
#3203330
0'
#3211143
0!
0.
b0 E
b1100 <
b1101101111101110111110111101010 F
1'
#3218956
0'
#3226769
1-
b1 E
1'
#3234582
0'
#3242395
b1101 &
1)
1!
0-
b10 E
b100000000000000000000000000000 G
1'
#3250208
0'
#3258021
1.
b11 E
1'
#3265834
0'
#3273647
0!
0.
b0 E
b1101 <
b11011011111011101111101111010101 F
1'
#3281460
0'
#3289273
1-
b1 E
1'
#3297086
0'
#3304899
b1110 &
1!
0-
b10 E
b1000000000000000000000000000000 G
1'
#3312712
0'
#3320525
1.
b11 E
1'
#3328338
0'
#3336151
0!
0.
b0 E
b1110 <
b10110111110111011111011110101011 F
1'
#3343964
0'
#3351777
1-
b1 E
1'
#3359590
0'
#3367403
b1111 &
0)
1!
0-
b10 E
b10000000000000000000000000000000 G
1'
#3375216
0'
#3383029
1.
b11 E
1'
#3390842
0'
#3398655
0!
0.
b0 E
b1111 <
b1101111101110111110111101010110 F
1'
#3406468
0'
#3414281
1-
b1 E
1'
#3422094
0'
#3429907
b10000 &
1)
1!
0-
b10 E
b0 G
1"
1'
#3437720
0'
#3445533
1.
b11 E
1'
#3453346
0'
#3461159
0!
0.
b0 E
b10000 <
b11011111011101111101111010101101 F
1'
#3468972
0'
#3476785
1-
b1 E
1'
#3484598
0'
#3492411
b10001 &
1!
0-
b10 E
0"
1'
#3500224
0'
#3508037
1.
b11 E
1'
#3515850
0'
#3523663
0!
0.
b0 E
b10001 <
b10111110111011111011110101011011 F
1'
#3531476
0'
#3539289
1-
b1 E
1'
#3547102
0'
#3554915
b10010 &
0)
1!
0-
b10 E
1'
#3562728
0'
#3570541
1.
b11 E
1'
#3578354
0'
#3586167
0!
0.
b0 E
b10010 <
b1111101110111110111101010110110 F
1'
#3593980
0'
#3601793
1-
b1 E
1'
#3609606
0'
#3617419
b10011 &
1)
1!
0-
b10 E
1'
#3625232
0'
#3633045
1.
b11 E
1'
#3640858
0'
#3648671
0!
0.
b0 E
b10011 <
b11111011101111101111010101101101 F
1'
#3656484
0'
#3664297
1-
b1 E
1'
#3672110
0'
#3679923
b10100 &
1!
0-
b10 E
1'
#3687736
0'
#3695549
1.
b11 E
1'
#3703362
0'
#3711175
0!
0.
b0 E
b10100 <
b11110111011111011110101011011011 F
1'
#3718988
0'
#3726801
1-
b1 E
1'
#3734614
0'
#3742427
b10101 &
1!
0-
b10 E
1'
#3750240
0'
#3758053
1.
b11 E
1'
#3765866
0'
#3773679
0!
0.
b0 E
b10101 <
b11101110111110111101010110110111 F
1'
#3781492
0'
#3789305
1-
b1 E
1'
#3797118
0'
#3804931
b10110 &
1!
0-
b10 E
1'
#3812744
0'
#3820557
1.
b11 E
1'
#3828370
0'
#3836183
0!
0.
b0 E
b10110 <
b11011101111101111010101101101111 F
1'
#3843996
0'
#3851809
1-
b1 E
1'
#3859622
0'
#3867435
b10111 &
1!
0-
b10 E
1'
#3875248
0'
#3883061
1.
b11 E
1'
#3890874
0'
#3898687
0!
0.
b0 E
b10111 <
b10111011111011110101011011011111 F
1'
#3906500
0'
#3914313
1-
b1 E
1'
#3922126
0'
#3929939
b11000 &
0)
1!
0-
b10 E
1'
#3937752
0'
#3945565
1.
b11 E
1'
#3953378
0'
#3961191
0!
0.
b0 E
b11000 <
b1110111110111101010110110111110 F
1'
#3969004
0'
#3976817
1-
b1 E
1'
#3984630
0'
#3992443
b11001 &
1)
1!
0-
b10 E
1'
#4000256
0'
#4008069
1.
b11 E
1'
#4015882
0'
#4023695
0!
0.
b0 E
b11001 <
b11101111101111010101101101111101 F
1'
#4031508
0'
#4039321
1-
b1 E
1'
#4047134
0'
#4054947
b11010 &
1!
0-
b10 E
1'
#4062760
0'
#4070573
1.
b11 E
1'
#4078386
0'
#4086199
0!
0.
b0 E
b11010 <
b11011111011110101011011011111011 F
1'
#4094012
0'
#4101825
1-
b1 E
1'
#4109638
0'
#4117451
b11011 &
1!
0-
b10 E
1'
#4125264
0'
#4133077
1.
b11 E
1'
#4140890
0'
#4148703
0!
0.
b0 E
b11011 <
b10111110111101010110110111110111 F
1'
#4156516
0'
#4164329
1-
b1 E
1'
#4172142
0'
#4179955
b11100 &
0)
1!
0-
b10 E
1'
#4187768
0'
#4195581
1.
b11 E
1'
#4203394
0'
#4211207
0!
0.
b0 E
b11100 <
b1111101111010101101101111101110 F
1'
#4219020
0'
#4226833
1-
b1 E
1'
#4234646
0'
#4242459
b11101 &
1)
1!
0-
b10 E
1'
#4250272
0'
#4258085
1.
b11 E
1'
#4265898
0'
#4273711
0!
0.
b0 E
b11101 <
b11111011110101011011011111011101 F
1'
#4281524
0'
#4289337
1-
b1 E
1'
#4297150
0'
#4304963
b11110 &
1!
0-
b10 E
1'
#4312776
0'
#4320589
1.
b11 E
1'
#4328402
0'
#4336215
0!
0.
b0 E
b11110 <
b11110111101010110110111110111011 F
1'
#4344028
0'
#4351841
1-
b1 E
1'
#4359654
0'
#4367467
b11111 &
1!
0-
b10 E
1'
#4375280
0'
#4383093
1.
b11 E
1'
#4390906
0'
#4398719
0!
0.
b0 E
b11111 <
b11101111010101101101111101110111 F
1'
#4406532
0'
#4414345
1-
b1 E
1'
#4422158
0'
#4429971
b100000 &
1!
0-
b10 E
1'
#4437784
0'
#4445597
1.
b11 E
1'
#4453410
0'
#4461223
0!
0.
b0 E
b11 H
b10 C
b11011110101011011011111011101111 ?
b11011110101011011011111011101111 F
1'
#4469036
0'
#4476849
b11011110101011011011111011101111 $
b11011110101011011011111011101111 >
b1 D
1%
1-
b1 E
1'
#4484662
0'
#4492475
1!
0-
b10 E
b10 D
1'
#4500288
0'
#4508101
b11 D
1.
b11 E
1'
#4515914
0'
#4523727
0!
0.
b0 E
b100 D
1'
#4531540
0'
#4539353
b101 D
1-
b1 E
1'
#4547166
0'
#4554979
1!
0-
b10 E
b110 D
1'
#4562792
0'
#4570605
b111 D
1.
b11 E
1'
#4578418
0'
#4586231
0!
0.
b0 E
b1000 D
1'
#4594044
0'
#4601857
b1001 D
1-
b1 E
1'
#4609670
0'
#4617483
1!
0-
b10 E
b1010 D
1'
#4625296
0'
#4633109
b1011 D
1.
b11 E
1'
#4640922
0'
#4648735
0!
0.
b0 E
b1100 D
1'
#4656548
0'
#4664361
b1101 D
1-
b1 E
1'
#4672174
0'
#4679987
1!
0-
b10 E
b1110 D
1'
#4687800
0'
#4695613
b1111 D
1.
b11 E
1'
#4703426
0'
#4711239
0!
0.
b0 E
b1 H
b10000000100000000000000000 /
b10 =
b0 D
1'
#4719052
0'
#4726865
b0 &
b10 H
b0 <
b10000000100000000000000000 G
0%
1-
b1 E
1'
#4734678
0'
#4742491
b1 &
1!
0-
b10 E
b100000001000000000000000000 G
1'
#4750304
0'
#4758117
1.
b11 E
1'
#4765930
0'
#4773743
0!
0.
b0 E
b1 <
b10111101010110110111110111011111 F
1'
#4781556
0'
#4789369
1-
b1 E
1'
#4797182
0'
#4804995
b10 &
1!
0-
b10 E
b1000000010000000000000000000 G
1'
#4812808
0'
#4820621
1.
b11 E
1'
#4828434
0'
#4836247
0!
0.
b0 E
b10 <
b1111010101101101111101110111111 F
1'
#4844060
0'
